{"bigweb_vue_routing.md":"CKMPhJ1Y","configdoc_show_whyfe.md":"CXdFQRK_","configdoc_show_bole.md":"mWlx2Ux1","changelog.md":"B9_0ipyL","ai_coze_juejin-hot-rank-bot.md":"B9ORcFHB","bigweb_js_blob.md":"BIJR7k-d","bigweb_browser_core.md":"DXlN1w8g","configdoc_newyear_2022.md":"CcSQ9gUc","bigweb_browser_block.md":"D1AyVKxl","bigweb_browser_problem.md":"s61K1YYG","bigweb_browser_chrome-devtools-study.md":"B9JHRXNr","ai_stable-diffusion_mac-install.md":"CD7ZuR_e","configdoc_show_whyfe-2024.md":"DRfLTNfk","ai_stable-diffusion_index.md":"I-ERxbPQ","coding_algorithm_headsort.md":"CIEJ64Vh","coding_algorithm_mergesort.md":"Yw3QSWRx","configdoc_top_notice.md":"CWtB4A4r","works_time-tools_time-tools-14.md":"CSS-FjOr","bigweb_js_delete.md":"BPiOdj-i","bigweb_es6_index.md":"BEjNRG-X","computerbase_internet_http.md":"TKDOUitS","bigweb_performance_image.md":"Bp7GFC2o","bigweb_js_p0.md":"PRjUHJ_G","bigweb_js_mybind.md":"DOuvrD9K","bigweb_vue_dep.md":"DQ2OdJF5","bigweb_js_es6_.md":"Bey6eWvE","bigweb_js_closure.md":"CCL2jDb-","technology_works_codenote.md":"BHkJXsjm","interview_code_kmp.md":"bbNzHVr4","bigweb_performance_throttling.md":"BbjSl5Q6","bigweb_css_ifc.md":"CeXyXdKh","bigweb_js_closureuse.md":"CiXBFQcr","interview_mini_index.md":"1qQn5t0n","interview_offer_p55-1.md":"DPb28UiK","interview_mini_principle.md":"B0fQPq1b","interview_offer_index.md":"g1vEPHZe","interview_offer_p50.md":"Bh9wwvP6","interview_offer_p54.md":"xFP2MszS","interview_offer_p53-2.md":"i6kWujM8","bigweb_js_copy.md":"BSZM1gF6","computerbase_internet_index.md":"c6uudSSy","technology_learn_node-require-json.md":"CqhCoEDR","computerbase_internet_tcp-udp.md":"CBeIakGA","technology_learn_nodejs-getting-started.md":"BvAUdbzo","computerbase_internet_tcp.md":"CuSQxlS7","technology_learn_png-compress.md":"BYjnRSE7","computerbase_internet_udp.md":"B9yzT3Pe","technology_learn_pnpm-issue-githubactions.md":"Djq_Qmix","technology_learn_qiniu-imgbed.md":"DdIe8uNm","technology_learn_qiniu-oss.md":"CCcJtSe5","computerbase_design_abstractfactory.md":"DZRsI7ZS","technology_learn_tool-methods.md":"CQowGT5c","technology_learn_tx-serverless-static.md":"DjveySM-","computerbase_design_factory.md":"LuCA3H0K","computerbase_design_index.md":"cFFjzgUX","interview_mini_feature.md":"B7fzJYmj","computerbase_design_single.md":"C04e8C0R","bigweb_js_changearr.md":"QOtWeord","technology_learn_tx-serverless-node.md":"C0J-mNaJ","bigweb_browser_eventloop.md":"D78HNQVo","works_time-tools_time-tools-15.md":"C5u2nW-W","configdoc_top_address.md":"BIFU4hJm","works_time-tools_time-tools-3.md":"BWnFwpDF","bigweb_js_getbool.md":"CofqTxPp","bigweb_css_p1.md":"BbXqFhJq","works_time-tools_time-tools-2.md":"BXNBAhhq","works_time-tools_time-tools-5.md":"wW2yR0GU","works_time-tools_time-tools-6.md":"Dp4EW2Jk","works_time-tools_time-tools-4.md":"CTrHU3lv","works_time-tools_time-tools-9.md":"Bv8bsald","bigweb_css_pseudo-element.md":"DsV9gGVI","bigweb_css_reflow.md":"tdTBRW5f","works_time-tools_time-tools-7.md":"BaYPF1Ut","computerbase_os_communicate.md":"BveIBphD","coding_github_index.md":"veRIg22G","coding_github_git删除当前分支下的所有历史版本与log并同步至github_git如何清除历史版本.md":"C4FR6HGR","computerbase_internet_clength.md":"B9z4mYHW","computerbase_os_deadlock.md":"9ze0lqE5","works_time-tools_time-tools-8.md":"8fu-lze7","technology_learn_jpg-compress.md":"BpbgXaNr","computerbase_os_thread.md":"DaomgrI_","bigweb_vue_diff.md":"Xqi3J8Cd","technology_learn_fixed-page.md":"BH_9Dh8r","essay_dev_2024-blog-perf.md":"DGpNcxPf","bigweb_vue_extend.md":"CFHITxZv","bigweb_vue_index.md":"CiymAbIW","bigweb_vue_hook.md":"CcrbpQZD","group.md":"IsnczKMQ","bigweb_vue_mechanism.md":"CzuYCV-H","bigweb_vue_keep-alive.md":"DJrPVMez","bigweb_vue_mixin.md":"D2I_Q2vl","bigweb_js_module.md":"CLk-B3B_","index.md":"NMGbhw5O","interview_code_debounce-throttle.md":"ONwdqESt","bigweb_css_selectors.md":"CEJKf7HV","bigweb_html_index.md":"DmsNpnS4","bigweb_vue_showif.md":"CoVsSiKW","interview_code_index.md":"BG6Kv4no","interview_code_middle-center.md":"DQYIOj_s","bigweb_html_semantic.md":"BjHVS01Z","interview_code_myclock.md":"XOsubJlN","interview_code_treetraverse.md":"CfUh3s47","bigweb_idea.md":"Ik4GDbJk","interview_code_transfer.md":"BsADCue2","computerbase_os_index.md":"TKTqE_aW","bigweb_js_apply.md":"BLaaYPXR","interview_internet_index.md":"Dyu8C8nr","computerbase_os_difprothr.md":"CmkxZhLZ","aboutme.md":"Drc1zyZL","bigweb_js_arrowfun.md":"PeBI9WIc","technology_learn_loadenv.md":"C4Xo782w","technology_learn_mergefile.md":"BU7Wh-LR","bigweb_css_bfc.md":"C__amlDk","bigweb_bun_bun-shell.md":"CI9jLFBj","bigweb_browser_index.md":"D7E_ldrl","bigweb_js_async.md":"DPX-wa9_","bigweb_js_asyncawait.md":"Dv4TbEx5","computerbase_os_process.md":"DHWnbgZL","bigweb_browser_cors.md":"C_3Rjtfy","bigweb_vue_responsive.md":"CWiu9D7O","bigweb_vueresource_index.md":"D3VyDlYq","bigweb_css_index.md":"Jwws5nf7","bigweb_vue_vnode.md":"Dv6hYert","coding_algorithm_addstring.md":"CwICmeH5","bigweb_js_currying.md":"Dcfn0q-j","coding_algorithm_feibo2.md":"D5LI9LkQ","coding_algorithm_feibo1.md":"Dxuzb6Yf","coding_algorithm_index.md":"C7d8kfeM","coding_algorithm_linkreserve.md":"Dy04LL7g","bigweb_js_deepclone.md":"CPrVjid3","coding_algorithm_judgesymmetrytree.md":"D_VVLSnZ","coding_algorithm_publicstring.md":"zwfX_pgi","coding_algorithm_publicstringlen.md":"Dj10LtTg","bigweb_js_diff-for-in-of.md":"Bzlyb-in","coding_algorithm_quicksort.md":"CfE_eMZY","bigweb_js_myapply.md":"BF8qapPi","bigweb_js_equala.md":"CusFgofb","bigweb_js_duplicate.md":"7J_LUj4e","bigweb_js_mycall.md":"C1NNyNzs","bigweb_js_es6.md":"BAL4Mjof","bigweb_js_throttling.md":"DTksetai","bigweb_js_numnotequal.md":"B0m7mf6n","bigweb_js_ecmathis.md":"DDZeQN4K","bigweb_js_objdiffprim.md":"CFNSKE0-","bigweb_js_equal.md":"C3PaOYGj","bigweb_js_nullobj.md":"aLOWbVme","bigweb_js_mynew.md":"DKFpmrH1","bigweb_js_event.md":"DQtHKgkO","bigweb_js_float.md":"Cf3q6UAa","bigweb_js_eventloop.md":"DpbLy4-l","bigweb_js_objparam.md":"CznOubpF","bigweb_js_index.md":"6p_p0jBV","bigweb_js_index copy.md":"C4FLIEtm","bigweb_js_onload-ready.md":"BQOJjFcO","bigweb_js_p2.md":"asug1XKV","bigweb_js_instanceof copy.md":"Bncda3YL","bigweb_js_instanceof.md":"og5NAwVm","computerbase_algorithm_index.md":"B7ZXWPKs","bigweb_js_p3.md":"CPyAtBkX","technology_source_objectid.md":"CL8lHm6R","bigweb_js_inherit.md":"Ch7BQ2ZH","bigweb_js_p4.md":"BB9V_Sqx","bigweb_js_judgedate.md":"4_yf6r9F","bigweb_js_primitivetype.md":"DXyke5Z8","bigweb_css_pseudo-class.md":"BcOAJPWe","bigweb_js_p1.md":"nZY7E1d5","bigweb_js_judgearr.md":"CRgOMWNQ","bigweb_js_likearray.md":"DfJRDQm2","bigweb_js_judgeobj.md":"BiPrCZOL","technology_learn_upyun.md":"BA8oGftO","bigweb_browser_safe.md":"Pb9QuzvQ","bigweb_js_promise copy.md":"D96Qez5e","technology_learn_ux.md":"ca6XfTKR","bigweb_css_flex.md":"B3wiPnT7","bigweb_js_typeof.md":"Cf2h902d","interview_mini_differentweb.md":"q_FvosSm","technology_learn_vitepress-plugin-rss.md":"DgHnjam8","bigweb_node_compress-response.md":"BbXZnKVj","bigweb_js_promiseall.md":"D_OhX1Fg","technology_study_chrome-debug1.md":"oQchmE4j","computerbase_leetcode_index.md":"C4kN1sIe","bigweb_js_mergerequest.md":"BXZzNDr3","technology_theory_index.md":"Bf0ELy8z","bigweb_js_runcontext.md":"DlHmAWnQ","technology_theory_serverless.md":"DMpSEB2s","bigweb_js_scope.md":"CWEFaJ5n","technology_tpl_index.md":"CkAANWNX","technology_study_ts-decorators.md":"CBs_JE3T","technology_tpl_uni-vue3-cli_1.md":"CC-4IBcB","bigweb_js_symbol.md":"BwrOYDLE","technology_tpl_uni-vue3-cli_2.md":"ykUhZ7Uq","technology_tpl_vite-vue3-template.md":"B2fMF88x","bigweb_js_this.md":"BwyIn5HT","technology_tpl_uni-vue3-cli_3.md":"CVFy4a4A","technology_tpl_web-sdk-tpl.md":"4BoCUi0K","technology_learn_webapck2vite.md":"3ZlS9P3X","technology_works_escheck.md":"CPozIBF8","technology_works_eslint-plugin-todo-ddl.md":"D6NzuvIx","technology_works_ewuit.md":"DJhSGaFw","technology_works_node-cli.md":"T12FIed8","technology_learn_webapck2vite2.md":"BZRvk24h","technology_works_fs-cli.md":"CcFY0Yhf","technology_works_index.md":"CVlVMVnz","technology_learn_yanglegeyang.md":"gP3HU-1Y","weekly_index.md":"Dhvt_qtS","works_time-lover_index.md":"Cfti9ZlR","works_time-tools_index.md":"V3B-n-Fb","works_time-lover_timelover-1.md":"BmV7YVnX","works_time-lover_timelover-2.md":"XJsR657E","works_time-tools_time-tools-10.md":"CYzkjcmC","works_time-tools_time-tools-11.md":"lm8t2r8T","interview_os_index.md":"kLwjiRaX","interview_other_index.md":"D0f2KFoU","interview_other_engineering.md":"LCr-TSpD","interview_other_inputurl.md":"COc1CUyd","works_time-tools_time-tools-1.md":"D-TZnLJl","interview_other_judgetype.md":"h9q9jj--","interview_other_object.md":"CbtYSkFR","interview_other_promote.md":"Dc9vVL4K","interview_other_prototype.md":"wPHep0c-","interview_performance_firstscreenrender.md":"Dnz1fSdB","interview_performance_index.md":"Bn47nmX1","interview_vue_index.md":"Cu65lqlM","stocks_precisionheadshot_index.md":"BGEU6rWm","stocks_sentimentcore_index.md":"C4emYCXf","technology_learn_cnnc.md":"C6cwbf0y","technology_learn_array-buffer.md":"DtXFFpWZ","technology_learn_deepin-wemeet.md":"DAT4k0jb","technology_learn_copy-branch.md":"Bgvvjvtn","technology_learn_deploy-preview-pr.md":"DQ4cRMDI","technology_learn_ep2-docker.md":"CS6qeVrY","technology_learn_eslint-plugin.md":"Bs0rCy2H","technology_source_core-decorators-1.md":"H3OeWk7E","technology_source_core-decorators-3.md":"-0wu0PdG","technology_source_core-decorators-2.md":"BoGjI6F6","technology_source_file-saver-source.md":"DN7kZlux","technology_source_index.md":"BMc8Rr3d","bigweb_css_box.md":"B297Bwk4","bigweb_js_p5.md":"GQXvETG5","bigweb_js_immed-setinterval.md":"CU4A5Utu","interview_offer_p58.md":"JnD6D_eT","bigweb_browser_render.md":"C128XFLz","interview_offer_p55.md":"BupMNAFb","bigweb_browser_storage.md":"B6W2asg4","works_time-tools_time-tools-13.md":"BFv_WTvB","bigweb_node_nvm-iterm.md":"DMynvVvv","bigweb_node_index.md":"BJl02Kz-","bigweb_js_getelement.md":"CYynTCa-","bigweb_node_standard-node-cli.md":"DjKsao8n","bigweb_performance_internet.md":"B-Go5KYZ","bigweb_performance_cdn.md":"BkR9XonK","configdoc_show_sw.md":"CSD4EEgv","bigweb_node_mongodb.md":"GetNLhzn","bigweb_node_phantom-dep-cli.md":"BDGzut2J","bigweb_performance_dnspre.md":"DznlOnqu","coding_algorithm_treeleveltraverse.md":"CqasGXTk","bigweb_js_valuepass.md":"BFflIYsV","bigweb_js_clock.md":"CsoVd9_n","bigweb_node_p1.md":"CCBLu3BQ","bigweb_js_variableobject.md":"A4AKaSuX","technology_learn_jsencrypt.md":"C0ctMolT","technology_learn_index.md":"D2YOjskd","bigweb_css_p2.md":"B7EQlBSw","bigweb_performance_ssr.md":"DETaOBye","technology_learn_mid-autumn-festival.md":"BUAlQ4IN","bigweb_performance_index.md":"_wdMwPtx","technology_learn_mini-lottie.md":"BYzruTrE","technology_learn_vite-plugin-monitor2.md":"CUaB4Lf6","technology_learn_vite-plugin-monitor1.md":"D8Nlcb5Q","bigweb_performance_lazyload.md":"BRpTB5yW","technology_learn_vite-plugin-monitor3.md":"DXNSuHMQ","technology_learn_vite-react-js.md":"yOARs66C","bigweb_performance_monitor.md":"CzshOLgn","bigweb_performance_prerender.md":"Cz_RkITn","technology_learn_esm-require.md":"Caf4jsla","bigweb_performance_preload.md":"CUhBlFhG","bigweb_regexp_p1.md":"CZJln7R6","bigweb_js_scopelink.md":"B58CvxtL","bigweb_regexp_index.md":"xupkPunS","bigweb_vue_compile.md":"ccOuDVyn","bigweb_vue_computed.md":"BgV7T8pf","bigweb_vue_communicate.md":"CsGz-All","bigweb_css_level.md":"BH2-8HSY","bigweb_js_runstack.md":"COm8OFRB","computerbase_algorithm_sort.md":"D0EJqRMO","technology_study_index.md":"C6i-wU9z","technology_study_chrome-debug6.md":"DDs01lC5","technology_learn_ssh-no-pwd-login.md":"Cn8_BXCN","technology_study_chrome-debug5.md":"18SnzxHd","technology_study_design-patterns1.md":"DCne1E2s","bigweb_js_typeconvert.md":"BsT1Tm5n","bigweb_js_garbage.md":"CRFziuML","technology_study_chrome-debug4.md":"B1cQsVES","technology_source_vite-loadenv.md":"Bayg_FzO","technology_study_chrome-debug3.md":"6Ya0IKhD","technology_study_design-patterns0.md":"tNbBZhrB","bigweb_js_prototype.md":"DXkqmOno","technology_study_chrome-debug2.md":"C4Iy23Vs","technology_works_theme.md":"AYkgUbXo","technology_works_html-inline-js-transform.md":"7GK6Zgce","technology_works_snippets.md":"DmGocfuc","technology_learn_window-var.md":"BuACaL9b","bigweb_js_v8garbage.md":"ClspuRPc","technology_works_share-snippets.md":"KZ4nGgUJ","technology_learn_js-cover.md":"d70mxJdJ","works_time-tools_time-tools-12.md":"DBw3tEon","technology_learn_forof-idx.md":"kKGB5CeR","technology_works_sm-cli.md":"C0-aOtHo","technology_learn_faas.md":"D4Zmhmmc","technology_works_online-resume.md":"DEqiRsGR","technology_study_http-proxy-fail.md":"DClBTU5w","technology_study_nvm-ls-remote.md":"BAQHKaqf","bigweb_browser_cache.md":"51m6_GOG","technology_learn_git-base.md":"sla_slI4","technology_works_vitepress-plugin-pagefind.md":"DIDEGTXS","bigweb_js_promise.md":"CANnuGC9","technology_study_design-patterns2.md":"BKw-riLD"}
