{"aboutme.md":"75CKzpt-","configdoc_show_sw.md":"BAP39_LA","configdoc_show_whyfe-2024.md":"dKncDO0F","configdoc_top_address.md":"D1oOqDBA","configdoc_top_notice.md":"JsJFntSn","ai_stable-diffusion_mac-install.md":"Coa7R-5i","ai_stable-diffusion_index.md":"A5ykCM2p","bigweb_browser_render.md":"BDUFRuvq","configdoc_show_bole.md":"B-aH6WPb","configdoc_newyear_2022.md":"DqwmHwfK","ai_coze_juejin-hot-rank-bot.md":"Crd9t29D","configdoc_show_whyfe.md":"BUKQFhsT","bigweb_html_semantic.md":"PMcayor4","bigweb_css_ifc.md":"DShypef6","bigweb_browser_index.md":"D3mDY-tn","bigweb_browser_cors.md":"BXLMtm81","bigweb_browser_cache.md":"BMIJzWHU","bigweb_browser_problem.md":"B4PL3qHy","bigweb_css_p2.md":"cDDNYKh1","bigweb_css_pseudo-class.md":"gfh0BryX","bigweb_css_bfc.md":"B0x3JNyV","bigweb_browser_core.md":"DwLcfj5s","bigweb_css_flex.md":"C1_Xe36K","computerbase_internet_clength.md":"C1iTLCWG","interview_code_myclock.md":"C4xFrW7s","interview_code_transfer.md":"BfVeOOVN","interview_code_middle-center.md":"D526uM7J","interview_mini_feature.md":"Ev3SY8lp","interview_internet_index.md":"DSZpP51j","interview_mini_differentweb.md":"Anlc3TA1","bigweb_js_p3.md":"CRGKICKG","interview_mini_principle.md":"LsOHQOWS","interview_offer_index.md":"zTIAi9YP","interview_mini_index.md":"CheUJ__U","bigweb_html_index.md":"B1JUTg3s","bigweb_es6_index.md":"D94hTkHb","bigweb_css_reflow.md":"Bzs_PBJL","bigweb_css_selectors.md":"D_P9PUyh","interview_code_treetraverse.md":"SDkcqlwy","bigweb_js_arrowfun.md":"BgjJ0rjz","bigweb_css_pseudo-element.md":"Bw6mDC7A","bigweb_js_delete.md":"DYLPle0-","bigweb_js_diff-for-in-of.md":"5AHhqTbs","bigweb_js_closure.md":"DdhXbhlH","technology_learn_webapck2vite2.md":"BeikfI2o","changelog.md":"D1qZjaaY","computerbase_internet_http.md":"-DxUTMna","technology_works_index.md":"Bfkll3yA","computerbase_os_process.md":"BHdo0YJI","bigweb_browser_storage.md":"DsknocGe","technology_study_chrome-debug3.md":"B3laYKpA","technology_study_chrome-debug4.md":"sa5SFspx","bigweb_js_changearr.md":"DSO9o49F","technology_tpl_vite-vue3-template.md":"Cxmp76yi","technology_learn_jsencrypt.md":"BVHcj0uJ","bigweb_performance_prerender.md":"BIlsdEvj","technology_tpl_web-sdk-tpl.md":"B77ogIC7","bigweb_js_es6_.md":"BPQjX2Sx","bigweb_js_clock.md":"YivXwv_L","bigweb_js_duplicate.md":"B0g9JOMy","bigweb_js_ecmathis.md":"BY-lKWa8","bigweb_js_closureuse.md":"DwqM_Ve1","bigweb_js_equala.md":"Ddt5fsby","bigweb_js_inherit.md":"DJ_S5vRI","bigweb_js_currying.md":"eGQLrmoZ","bigweb_browser_eventloop.md":"Dbso8FNe","technology_learn_mini-lottie.md":"D3BzbwN0","bigweb_js_asyncawait.md":"Cuy7kl8x","bigweb_js_apply.md":"_9vcgkUV","bigweb_js_equal.md":"CRzYPsmU","bigweb_js_judgearr.md":"81y1OAet","technology_learn_eslint-plugin.md":"D-3LfSsm","bigweb_js_blob.md":"CYQcu-Ch","technology_learn_esm-require.md":"CtfzhqcE","bigweb_js_mergerequest.md":"iw_cQwXC","bigweb_js_copy.md":"HQCZ64Y-","bigweb_browser_safe.md":"D4GXgJ4q","coding_algorithm_index.md":"B-anvPNs","bigweb_idea.md":"DIuMpX9d","bigweb_css_index.md":"YBhnltkg","bigweb_js_likearray.md":"DIjfBMbt","bigweb_js_judgedate.md":"BIrHJAML","bigweb_js_nullobj.md":"DiSLAJFz","coding_algorithm_linkreserve.md":"DrdeuC8H","bigweb_js_objdiffprim.md":"BbSfdjLn","coding_algorithm_mergesort.md":"COlAI-YT","bigweb_js_numnotequal.md":"Ca3L0X_D","coding_algorithm_publicstring.md":"BDezv83M","bigweb_js_onload-ready.md":"CZrxKhob","bigweb_js_objparam.md":"2Oe2lQkM","coding_algorithm_publicstringlen.md":"Si9WWYBJ","bigweb_js_p0.md":"CDKBhG0U","coding_github_git删除当前分支下的所有历史版本与log并同步至github_git如何清除历史版本.md":"DaGP0CTn","bigweb_js_p5.md":"DZzRkz5C","bigweb_js_primitivetype.md":"DXuul_EY","bigweb_css_box.md":"Cpuo7q7D","coding_algorithm_treeleveltraverse.md":"Dmygt2Bd","bigweb_js_promise copy.md":"CE5Efdbn","bigweb_js_p2.md":"X6Ku1pe0","interview_offer_p50.md":"C77L0PZG","coding_github_index.md":"Cs1KmryU","technology_learn_mergefile.md":"Di49hfeA","bigweb_js_prototype.md":"BemJVD44","computerbase_internet_index.md":"CDarlCzu","interview_offer_p53-2.md":"C1LXYmKR","bigweb_js_runstack.md":"DrJaeIWm","technology_learn_mid-autumn-festival.md":"BNVWJ_U0","bigweb_js_runcontext.md":"D7sFfOGW","computerbase_internet_tcp-udp.md":"C5aVuzxJ","interview_offer_p54.md":"wNJBc-YW","bigweb_js_scope.md":"Dxko5n1m","technology_learn_node-require-json.md":"DEP4WNPm","interview_offer_p55-1.md":"46ceRELF","bigweb_js_scopelink.md":"CE-kBcSr","technology_learn_nodejs-getting-started.md":"DEjc-cwB","computerbase_internet_udp.md":"e7pLTUVr","computerbase_internet_tcp.md":"BJ1mvDWo","interview_offer_p55.md":"BNDZQBs9","technology_learn_pnpm-issue-githubactions.md":"CY-zy2HM","computerbase_algorithm_index.md":"DyMzNGVh","bigweb_js_symbol.md":"C6cIwmIq","bigweb_js_throttling.md":"C1pDuMta","technology_learn_png-compress.md":"656c5wsO","bigweb_js_this.md":"2rC1YaaZ","computerbase_design_abstractfactory.md":"EdZ0J6Wt","computerbase_design_factory.md":"jQU72sYC","bigweb_js_typeof.md":"CmWrLv1r","technology_learn_qiniu-imgbed.md":"DTbN7UBX","technology_learn_ssh-no-pwd-login.md":"BrzMoLw8","computerbase_design_index.md":"Yg2N8QBI","technology_learn_qiniu-oss.md":"iJ03EuYd","interview_other_inputurl.md":"CoXyn9SP","bigweb_js_v8garbage.md":"BVdiKy_b","computerbase_design_single.md":"DogdCiOg","bigweb_js_valuepass.md":"CMJSLmoA","interview_other_promote.md":"S-MYpqCg","interview_other_judgetype.md":"DG_DpHB9","technology_learn_tx-serverless-static.md":"J5QzQ1-Q","bigweb_node_compress-response.md":"pJnF74J0","bigweb_node_index.md":"Crl7yc4S","computerbase_os_difprothr.md":"DdltsU8g","computerbase_os_deadlock.md":"CA38DhBg","technology_learn_ux.md":"gLFnNAZz","interview_other_prototype.md":"BZDhAg3j","technology_learn_vite-plugin-monitor1.md":"D9Vdjn84","bigweb_js_variableobject.md":"Af_BJ0pX","interview_performance_firstscreenrender.md":"Cgvh83yo","bigweb_node_mongodb.md":"CY5Yy3pM","technology_learn_vite-plugin-monitor2.md":"DtYJX6Fq","bigweb_node_nvm-iterm.md":"Dq7-MeS9","technology_learn_vite-plugin-monitor3.md":"56tJENE3","bigweb_node_p1.md":"C9ymsXEX","computerbase_os_thread.md":"DHFgr9Ou","technology_learn_vite-react-js.md":"DcXhIrHF","stocks_precisionheadshot_index.md":"CNRMenfC","essay_dev_2024-blog-perf.md":"Bpm2OhmQ","stocks_sentimentcore_index.md":"CffE2M9z","bigweb_node_phantom-dep-cli.md":"DJmMbjEJ","technology_learn_array-buffer.md":"CFty-f0n","bigweb_node_standard-node-cli.md":"Ud6azys_","bigweb_performance_internet.md":"TLemvdDj","technology_learn_cnnc.md":"iqNSYjFy","group.md":"uysouuJn","bigweb_performance_cdn.md":"BwcwqCiW","interview_code_debounce-throttle.md":"sGc0BW2Y","index.md":"Dbo53yEb","interview_code_index.md":"DExuvi4a","interview_code_kmp.md":"Cmzxe_rV","works_time-tools_time-tools-6.md":"C9ZOvoIB","technology_learn_deepin-wemeet.md":"g0T8CKNU","technology_learn_ep2-docker.md":"Bph4k2wW","technology_learn_window-var.md":"yIceXe1u","technology_learn_copy-branch.md":"4F21E-iW","technology_learn_deploy-preview-pr.md":"BnhsOZvY","technology_source_core-decorators-1.md":"mzegvPrq","technology_learn_yanglegeyang.md":"z9Y1xbqr","technology_source_core-decorators-2.md":"BhxGVkNA","technology_source_core-decorators-3.md":"DJXHVNNA","bigweb_performance_dnspre.md":"MpfXCOXa","technology_learn_faas.md":"Dm1KiRKG","technology_source_file-saver-source.md":"B3o6q1YW","bigweb_performance_image.md":"fWyLYmSL","technology_learn_fixed-page.md":"DuVYfxvW","technology_source_index.md":"CuHSWTzA","bigweb_performance_index.md":"BnUYNG3e","technology_learn_forof-idx.md":"Dde_zX-i","technology_learn_webapck2vite.md":"BFxuBE0A","technology_learn_git-base.md":"sUXowzUb","technology_tpl_uni-vue3-cli_1.md":"C4gfxOmg","bigweb_performance_monitor.md":"r86AxRtK","technology_source_vite-loadenv.md":"Csjd6Pk4","bigweb_performance_preload.md":"mAIC8nbl","technology_study_chrome-debug1.md":"Cuyhe3Qu","technology_learn_jpg-compress.md":"BqHphewK","bigweb_performance_ssr.md":"D5VWwq2Y","technology_study_chrome-debug2.md":"E18-J86u","technology_study_chrome-debug5.md":"BQ4xaPaV","technology_tpl_uni-vue3-cli_3.md":"CO2IRZKm","technology_tpl_uni-vue3-cli_2.md":"CDAU9UAZ","technology_learn_loadenv.md":"CiL16iSn","technology_study_chrome-debug6.md":"B17MoD7-","technology_study_design-patterns0.md":"Bt5Dq3Jn","bigweb_performance_throttling.md":"CDM2otbG","bigweb_regexp_index.md":"13-a2FrW","technology_study_design-patterns1.md":"DrPMzVq_","technology_works_codenote.md":"BiLcH5XV","bigweb_regexp_p1.md":"6b38X5B-","bigweb_vue_communicate.md":"NrLjdPl_","technology_study_design-patterns2.md":"CzswleJS","bigweb_vue_compile.md":"BeIRw3lf","technology_study_http-proxy-fail.md":"CJxo6iml","technology_study_nvm-ls-remote.md":"-QVHddq9","technology_works_escheck.md":"DkQAtI0g","bigweb_vue_computed.md":"CHibXdRe","technology_works_theme.md":"01hoecRz","technology_study_index.md":"DiCE7ahb","bigweb_vue_dep.md":"DAxzSZ7y","technology_works_ewuit.md":"BbMZSDsn","technology_works_eslint-plugin-todo-ddl.md":"CQd88IRH","technology_study_ts-decorators.md":"B69kMypP","bigweb_vue_diff.md":"DjXvxoWs","technology_theory_index.md":"CYz7um9t","bigweb_vue_extend.md":"CN0uFEA4","technology_tpl_index.md":"DjXVwKLk","bigweb_vue_mechanism.md":"BCjJdcXU","works_time-lover_index.md":"D4Ldc2jH","bigweb_vue_mixin.md":"BsEQHnHQ","works_time-lover_timelover-1.md":"BPu8vwIk","technology_works_snippets.md":"zWx07ahv","technology_works_sm-cli.md":"C30Wjncr","bigweb_vue_responsive.md":"UPJDFlgb","bigweb_vue_routing.md":"Do_kRP7G","works_time-tools_index.md":"B0BcVtrd","works_time-lover_timelover-2.md":"sHviEJtD","works_time-tools_time-tools-14.md":"09luS_CV","works_time-tools_time-tools-15.md":"B9lvFoJ8","bigweb_vue_showif.md":"BTju1ujH","works_time-tools_time-tools-2.md":"iK3fME8D","works_time-tools_time-tools-1.md":"BTuOyDLV","bigweb_vue_vnode.md":"BBk7GHcy","works_time-tools_time-tools-10.md":"BZ-orTnD","works_time-tools_time-tools-3.md":"Czp1PXya","bigweb_vueresource_index.md":"BtA-f1gY","works_time-tools_time-tools-4.md":"DfOOl5X-","coding_algorithm_addstring.md":"QaFivyfj","works_time-tools_time-tools-5.md":"CHX5U_wt","coding_algorithm_feibo1.md":"_Rh7rIcU","works_time-tools_time-tools-11.md":"DLAWi1Tu","coding_algorithm_feibo2.md":"DcYngCHS","works_time-tools_time-tools-7.md":"nNHzi6rN","works_time-tools_time-tools-13.md":"ClEwUP63","bigweb_js_p4.md":"DkmaHMUU","coding_algorithm_headsort.md":"DTmCoq93","works_time-tools_time-tools-8.md":"CRDw3bMN","bigweb_js_async.md":"BZGIrOSn","bigweb_js_index copy.md":"TnURyT3Q","bigweb_js_es6.md":"WEuP8np5","bigweb_js_p1.md":"CsrNW2z2","bigweb_js_judgeobj.md":"DasZq-Pt","bigweb_js_event.md":"Cn1mHbLY","computerbase_os_index.md":"C9cA-rCx","bigweb_js_deepclone.md":"CPNkOLKm","bigweb_js_index.md":"B_62ivzm","bigweb_js_promise.md":"D0HGEPAj","bigweb_js_myapply.md":"BB6o1sYe","technology_learn_tx-serverless-node.md":"C3YB9WYh","technology_learn_js-cover.md":"BUtrFz-_","technology_learn_index.md":"1miNpZpn","bigweb_js_typeconvert.md":"DnTc4TQc","technology_learn_tool-methods.md":"BhXG7lVn","bigweb_browser_block.md":"C-T5Y2HB","interview_vue_index.md":"BlEAWQvi","bigweb_js_immed-setinterval.md":"Bp9vIQda","bigweb_js_getelement.md":"CYzROAAt","technology_learn_vitepress-plugin-rss.md":"BrV_NXmK","bigweb_js_float.md":"CRxgVKcJ","bigweb_js_eventloop.md":"DM37v7P9","bigweb_js_garbage.md":"E5JCzCYn","bigweb_js_getbool.md":"COMQYdGQ","bigweb_js_promiseall.md":"C9_yONsz","coding_algorithm_quicksort.md":"cf0WH5dB","interview_offer_p58.md":"BvWmZwnr","interview_performance_index.md":"reDSVPSX","computerbase_algorithm_sort.md":"Booptq-E","computerbase_leetcode_index.md":"BgIEs8Cp","interview_other_index.md":"BUvndfS7","bigweb_vue_hook.md":"BVR65vC2","interview_os_index.md":"BOyBI-bd","interview_other_engineering.md":"DsSVIPkt","weekly_index.md":"Dd3SWGQR","bigweb_browser_chrome-devtools-study.md":"CkHBzR8Y","works_time-tools_time-tools-9.md":"BFVB7kyE","bigweb_css_level.md":"DS0k3clX","technology_works_html-inline-js-transform.md":"wMw1q9xL","works_time-tools_time-tools-12.md":"CXjUx3GK","bigweb_bun_bun-shell.md":"xAr0GaNh","bigweb_js_module.md":"BLQUlIuo","bigweb_js_mycall.md":"ByViALMB","bigweb_js_mynew.md":"CIjuJ_gy","coding_algorithm_judgesymmetrytree.md":"DJmmmYF_","bigweb_css_p1.md":"DIJHiV_M","computerbase_os_communicate.md":"DqMtcJWK","interview_other_object.md":"1zj6UTwW","bigweb_js_mybind.md":"DTvmR7wi","bigweb_performance_lazyload.md":"B3jO1T37","technology_works_fs-cli.md":"C46Zfnd1","technology_source_objectid.md":"BHeYYGFo","technology_theory_serverless.md":"BEeQyIyu","technology_works_share-snippets.md":"Cyu7scUt","technology_learn_upyun.md":"tZfNWx98","technology_works_vitepress-plugin-pagefind.md":"CUk2rko_","bigweb_vue_index.md":"C6HzIXRe","technology_works_node-cli.md":"Co8FT5TS","bigweb_vue_keep-alive.md":"qvslPbrD","bigweb_js_instanceof.md":"9dBoQGSL","bigweb_js_instanceof copy.md":"CiAxVgu0","technology_works_online-resume.md":"C0zSoDUG"}
