{"aboutme.md":"CXyZkM0y","ai_coze_juejin-hot-rank-bot.md":"CaGH0sxw","ai_stable-diffusion_index.md":"Dx06p1b0","ai_stable-diffusion_mac-install.md":"ByYud2ZH","bigweb_browser_block.md":"BJjekzcd","bigweb_browser_cache.md":"CCSjEW0u","bigweb_browser_chrome-devtools-study.md":"BT4tx7KV","bigweb_browser_core.md":"bPIus6GU","bigweb_browser_cors.md":"BuKzYY1a","bigweb_browser_eventloop.md":"VS003AjD","bigweb_browser_index.md":"BFkZj6Ab","bigweb_browser_problem.md":"DUUv26PV","bigweb_browser_render.md":"BeXj00E5","bigweb_browser_safe.md":"Cxo2fpxN","bigweb_browser_storage.md":"X2XukXni","bigweb_bun_bun-shell.md":"DRtGIpFh","bigweb_css_bfc.md":"CnEiRXSz","bigweb_css_box.md":"xOVAs2wv","bigweb_css_flex.md":"DVkvRaK0","bigweb_css_ifc.md":"DYkgIpD5","bigweb_css_index.md":"NU1GTGRQ","bigweb_css_level.md":"DqNiKg6k","bigweb_css_p1.md":"BREpi4Qp","bigweb_css_p2.md":"DP4voZLZ","bigweb_css_pseudo-class.md":"heW_Z0YV","bigweb_css_pseudo-element.md":"suNjj5Oo","bigweb_css_reflow.md":"BuueosIy","bigweb_css_selectors.md":"9Dtbr1n4","bigweb_es6_index.md":"43nQ6d4n","bigweb_html_index.md":"CeIfCcHf","bigweb_html_semantic.md":"DcUMtyUN","bigweb_idea.md":"D8SDIJJl","bigweb_js_apply.md":"DtLxUgEX","bigweb_js_arrowfun.md":"BiwBUokZ","bigweb_js_async.md":"D45-yCai","bigweb_js_asyncawait.md":"CTu7xus7","bigweb_js_blob.md":"Crn59R1e","bigweb_js_changearr.md":"UpNv0yW9","bigweb_js_clock.md":"d8eK37PT","bigweb_js_closure.md":"M8lYO0TS","bigweb_js_closureuse.md":"Icw_mhlc","bigweb_js_copy.md":"BcJPPb6h","bigweb_js_currying.md":"DpPlSQ8k","bigweb_js_deepclone.md":"BTDco1CE","bigweb_js_delete.md":"C7opgNoC","bigweb_js_diff-for-in-of.md":"BufKX8e8","bigweb_js_duplicate.md":"CuDli7au","bigweb_js_ecmathis.md":"CEo04YqB","bigweb_js_equal.md":"Bt9YtOym","bigweb_js_equala.md":"DGqFhs2p","bigweb_js_es6.md":"BMrR5h_A","bigweb_js_es6_.md":"D4Yo5vMS","bigweb_js_event.md":"C7cnMjVc","bigweb_js_eventloop.md":"BdE8DSp3","bigweb_js_float.md":"B62sS8ij","bigweb_js_garbage.md":"DmsD-CT4","bigweb_js_getbool.md":"CpMr42Jj","bigweb_js_getelement.md":"BVFWZtCi","bigweb_js_immed-setinterval.md":"B7FHFx6W","bigweb_js_index copy.md":"CF2PcQsH","bigweb_js_index.md":"4RVvbXnX","bigweb_js_inherit.md":"DtJtp19p","bigweb_js_instanceof copy.md":"CfCENQR9","bigweb_js_instanceof.md":"DDcOnohc","bigweb_js_judgearr.md":"DQnhAoLJ","bigweb_js_judgedate.md":"BH43EsW_","bigweb_js_judgeobj.md":"B_zqokfu","bigweb_js_likearray.md":"DLuBcFwQ","bigweb_js_mergerequest.md":"Bv7_aC9M","bigweb_js_module.md":"DGX4K-XC","bigweb_js_myapply.md":"BgG6lp5i","bigweb_js_mybind.md":"BFAna-Kq","bigweb_js_mycall.md":"BhmEuSk4","bigweb_js_mynew.md":"b17dO_sm","bigweb_js_nullobj.md":"DUm8zsdK","bigweb_js_numnotequal.md":"BY2MJl5E","bigweb_js_objdiffprim.md":"yBW7oAUR","bigweb_js_objparam.md":"CtThUDBl","bigweb_js_onload-ready.md":"J7lYX51o","bigweb_js_p0.md":"B7e6Mk22","bigweb_js_p1.md":"BA5kDCjV","bigweb_js_p2.md":"BcgBOMYa","bigweb_js_p3.md":"CySz3C1Y","bigweb_js_p4.md":"B3toku12","bigweb_js_p5.md":"QAUaWVBs","bigweb_js_primitivetype.md":"BYEDhcMe","bigweb_js_promise copy.md":"D5VnWloe","bigweb_js_promise.md":"BgisFc6p","bigweb_js_promiseall.md":"C7MF9_zJ","bigweb_js_prototype.md":"DpRumxsP","bigweb_js_runcontext.md":"CteJ4H1a","bigweb_js_runstack.md":"YoqQFche","bigweb_js_scope.md":"RSIFBbgl","bigweb_js_scopelink.md":"Bkpa2yl-","bigweb_js_symbol.md":"238Tfj6K","bigweb_js_this.md":"j5NFIHwe","bigweb_js_throttling.md":"dMpGg6d2","bigweb_js_typeconvert.md":"BK2yEJmW","bigweb_js_typeof.md":"CjNnizcP","bigweb_js_v8garbage.md":"Bs0MYOwe","bigweb_js_valuepass.md":"DGXx3Gqh","bigweb_js_variableobject.md":"D7cjarNm","bigweb_node_compress-response.md":"BSKhj749","bigweb_node_index.md":"CvcbYHNM","bigweb_node_mongodb.md":"DqWOKwLb","bigweb_node_nvm-iterm.md":"Bdl4n6fW","bigweb_node_p1.md":"C4rGwrWS","bigweb_node_phantom-dep-cli.md":"Dk1C3sCx","bigweb_node_standard-node-cli.md":"BbLL8srV","bigweb_node_前端接口神器之 json-server 详细使用指南 - megasu - 博客园.md":"CJLKI05e","bigweb_performance_cdn.md":"DKcrBIwZ","bigweb_performance_dnspre.md":"Bsb9tfqO","bigweb_performance_image.md":"DiOtUrUq","bigweb_performance_index.md":"Cp3hmy4A","bigweb_performance_internet.md":"CkHl1s7S","bigweb_performance_lazyload.md":"CVz1GAHE","bigweb_performance_monitor.md":"RTTgrQUU","bigweb_performance_preload.md":"CU_Ja0jp","bigweb_performance_prerender.md":"Bvi82wKm","bigweb_performance_ssr.md":"SyaFEGKS","bigweb_performance_throttling.md":"Dxe5nitf","bigweb_regexp_index.md":"C4IXhQWX","bigweb_regexp_p1.md":"YbtvI8S8","bigweb_vue_communicate.md":"Beahks4_","bigweb_vue_compile.md":"T3kAtfpm","bigweb_vue_computed.md":"fnV0fJ2I","bigweb_vue_dep.md":"1WvOH4QE","bigweb_vue_diff.md":"BT6pG7WK","bigweb_vue_extend.md":"DCksJbY6","bigweb_vue_hook.md":"CCfwWwIm","bigweb_vue_index.md":"BoqkRhZW","bigweb_vue_keep-alive.md":"DUi2W2pf","bigweb_vue_mechanism.md":"C_gDER5o","bigweb_vue_mixin.md":"BhV1odtf","bigweb_vue_responsive.md":"D_BWDj4p","bigweb_vue_routing.md":"C7JWw-rD","bigweb_vue_showif.md":"B9No_KFp","bigweb_vue_vnode.md":"JJ7t4FyF","bigweb_vueresource_index.md":"BX_XzfKd","changelog.md":"DSp8gs3D","coding_algorithm_addstring.md":"CcYM9k5-","coding_algorithm_feibo1.md":"us8TpS76","coding_algorithm_feibo2.md":"CUubF-pj","coding_algorithm_headsort.md":"BqSCvGh6","coding_algorithm_index.md":"Be2YbHG8","coding_algorithm_judgesymmetrytree.md":"BkJHQ2Pt","coding_algorithm_linkreserve.md":"Bwbp2AKt","coding_algorithm_mergesort.md":"DStRHwEg","coding_algorithm_publicstring.md":"6S-00lo3","coding_algorithm_publicstringlen.md":"CN-tA0CN","coding_algorithm_quicksort.md":"KgDQjeLm","coding_algorithm_treeleveltraverse.md":"XB876lQg","coding_github_git删除当前分支下的所有历史版本与log并同步至github_git如何清除历史版本.md":"DeyzqHI8","coding_github_index.md":"CCD3Ctu1","computerbase_algorithm_index.md":"DFjg-Gtv","computerbase_algorithm_sort.md":"BuklI2hJ","computerbase_design_abstractfactory.md":"DPIVChYL","computerbase_design_factory.md":"CVP06nJx","computerbase_design_index.md":"D37nFJ6G","computerbase_design_single.md":"Dy4Oesb0","computerbase_internet_clength.md":"ohEBkJt9","computerbase_internet_http.md":"kJ1lqJA4","computerbase_internet_index.md":"DKi3jNvv","computerbase_internet_tcp-udp.md":"DXdTlDvp","computerbase_internet_tcp.md":"XEw-GDiQ","computerbase_internet_udp.md":"Bix63nPz","computerbase_leetcode_index.md":"CLtG5jNj","computerbase_os_communicate.md":"CODvWKLo","computerbase_os_deadlock.md":"BY1nwmxO","computerbase_os_difprothr.md":"BJYiwnzk","computerbase_os_index.md":"DQ81MGt0","computerbase_os_process.md":"D2bYdJI1","computerbase_os_thread.md":"af-t-6oO","configdoc_newyear_2022.md":"DygaKl-U","configdoc_show_bole.md":"B5i-RwPY","configdoc_show_sw.md":"6j1DBVvI","configdoc_show_whyfe-2024.md":"D_JwOHFJ","configdoc_show_whyfe.md":"Cx7e-Qyi","configdoc_top_address.md":"DtDyCHcc","configdoc_top_notice.md":"C8nIg-wd","essay_dev_2024-blog-perf.md":"HA6Y-GSN","group.md":"JmVOUUD9","index.md":"BX0cCQdk","interview_code_debounce-throttle.md":"DT6eDBZM","interview_code_index.md":"D77JfGnJ","interview_code_kmp.md":"Blq-haor","interview_code_middle-center.md":"D6HZpjd6","interview_code_myclock.md":"BteKH9fe","interview_code_transfer.md":"Sv-tjNgc","interview_code_treetraverse.md":"Ciil8hJs","interview_internet_index.md":"DyG3JyyY","interview_mini_differentweb.md":"B1NkonvE","interview_mini_feature.md":"D6_BKpPZ","interview_mini_index.md":"HttcQTTv","interview_mini_principle.md":"DnvmalvB","interview_offer_index.md":"CPwLHZwe","interview_offer_p50.md":"BwjLjyXL","interview_offer_p53-2.md":"BUVRN3Ah","interview_offer_p54.md":"C1CbfDEh","interview_offer_p55-1.md":"DfevGSZ9","interview_offer_p55.md":"DIMvoDMQ","interview_offer_p58.md":"BAKjauen","interview_os_index.md":"mHeRUUqE","interview_other_engineering.md":"B5KOxevx","interview_other_index.md":"BfAX6y2_","interview_other_inputurl.md":"Cmyz0b1i","interview_other_judgetype.md":"C9qWbj8N","interview_other_object.md":"bAcK0jAq","interview_other_promote.md":"D2rFrup3","interview_other_prototype.md":"BHU_yegh","interview_performance_firstscreenrender.md":"LSJDlKyP","interview_performance_index.md":"CLXYMjq6","interview_vue_index.md":"BNI9ddTo","stocks_precisionheadshot_index.md":"p2a47hHB","stocks_sentimentcore_index.md":"Dai4FEMe","technology_learn_array-buffer.md":"Cgb3wXON","technology_learn_cnnc.md":"CQPSeLuJ","technology_learn_copy-branch.md":"4SUJGgzc","technology_learn_deepin-wemeet.md":"kENyncSG","technology_learn_deploy-preview-pr.md":"Cn7g7nP3","technology_learn_ep2-docker.md":"D6QLayV-","technology_learn_eslint-plugin.md":"yRxyffNR","technology_learn_esm-require.md":"GEhNLm8f","technology_learn_faas.md":"6BkysTZx","technology_learn_fixed-page.md":"CcU7FnUX","technology_learn_forof-idx.md":"CWTRlSPa","technology_learn_git-base.md":"DOQHPQS5","technology_learn_index.md":"BvOCj2_M","technology_learn_jpg-compress.md":"JAEecQ1c","technology_learn_js-cover.md":"BACNnc6w","technology_learn_jsencrypt.md":"A01WKqNr","technology_learn_loadenv.md":"Dd2dhfi0","technology_learn_mergefile.md":"ESyLP462","technology_learn_mid-autumn-festival.md":"CF4FnFGF","technology_learn_mini-lottie.md":"CZ3pdZHF","technology_learn_node-require-json.md":"Cejub_X6","technology_learn_nodejs-getting-started.md":"CYr1Iz_Y","technology_learn_png-compress.md":"ChzqLWuR","technology_learn_pnpm-issue-githubactions.md":"CElg-hM5","technology_learn_qiniu-imgbed.md":"B08-5XGL","technology_learn_qiniu-oss.md":"CuiIMMtP","technology_learn_ssh-no-pwd-login.md":"DVlpnrWT","technology_learn_tool-methods.md":"o09K-7z4","technology_learn_tx-serverless-node.md":"XS__AvAC","technology_learn_tx-serverless-static.md":"DjpcxUWy","technology_learn_upyun.md":"CAx64uiC","technology_learn_ux.md":"Dd3_-puA","technology_learn_vite-plugin-monitor1.md":"DWx2XqAD","technology_learn_vite-plugin-monitor2.md":"pxGkcSsK","technology_learn_vite-plugin-monitor3.md":"ClpSMAYe","technology_learn_vite-react-js.md":"D2GLR8NL","technology_learn_vitepress-plugin-rss.md":"CHK9cRPj","technology_learn_webapck2vite.md":"CQV9ow0h","technology_learn_webapck2vite2.md":"DDW790M_","technology_learn_window-var.md":"BgH6JdKq","technology_learn_yanglegeyang.md":"BOfobmmz","technology_source_core-decorators-1.md":"DWgUONfw","technology_source_core-decorators-2.md":"Dts17FXN","technology_source_core-decorators-3.md":"Dq6ZAXjI","technology_source_file-saver-source.md":"DGt9nU7O","technology_source_index.md":"BMNBiMwp","technology_source_objectid.md":"3DSlovOk","technology_source_vite-loadenv.md":"_MQtyr9n","technology_study_chrome-debug1.md":"BmBouoxp","technology_study_chrome-debug2.md":"D_hXTJCI","technology_study_chrome-debug3.md":"Dkai04wY","technology_study_chrome-debug4.md":"D8OWig1p","technology_study_chrome-debug5.md":"C11EKzpy","technology_study_chrome-debug6.md":"ayGiq1BT","technology_study_design-patterns0.md":"BxpUQIZ9","technology_study_design-patterns1.md":"CJmULOVa","technology_study_design-patterns2.md":"CTizreYe","technology_study_http-proxy-fail.md":"H3QFHxl5","technology_study_index.md":"Cz5I_n1Y","technology_study_nvm-ls-remote.md":"Dk1EvS1u","technology_study_ts-decorators.md":"BonwpEf-","technology_theory_index.md":"peINxbVg","technology_theory_serverless.md":"D1SU-Hg1","technology_tpl_index.md":"Bk6f5ywZ","technology_tpl_uni-vue3-cli_1.md":"BtLbEKSY","technology_tpl_uni-vue3-cli_2.md":"BHNQEkXu","technology_tpl_uni-vue3-cli_3.md":"BqFf8yY6","technology_tpl_vite-vue3-template.md":"C5ulC4Du","technology_tpl_web-sdk-tpl.md":"DhkSn9qb","technology_works_codenote.md":"CaqDXtYG","technology_works_escheck.md":"B3ISaMy5","technology_works_eslint-plugin-todo-ddl.md":"C03ghC8M","technology_works_ewuit.md":"Bs_DX6WR","technology_works_fs-cli.md":"FCEoZPXS","technology_works_html-inline-js-transform.md":"C_ThFOJO","technology_works_index.md":"C2SG17LO","technology_works_node-cli.md":"Bu4u1sYO","technology_works_online-resume.md":"CKaWEf7V","technology_works_share-snippets.md":"sTwRIMZK","technology_works_sm-cli.md":"DSzwgocg","technology_works_snippets.md":"TL5CC4WR","technology_works_theme.md":"B8Lv1kTa","technology_works_vitepress-plugin-pagefind.md":"CBsXixQa","weekly_index.md":"BeWYzCf_","works_time-lover_index.md":"CFssOv1y","works_time-lover_timelover-1.md":"BclwFPMX","works_time-lover_timelover-2.md":"CQjn-w3l","works_time-tools_index.md":"VIS7sSvm","works_time-tools_time-tools-1.md":"jMk1Jv5J","works_time-tools_time-tools-10.md":"CA2DbHZc","works_time-tools_time-tools-11.md":"CnIhMNDk","works_time-tools_time-tools-12.md":"BOyU93KB","works_time-tools_time-tools-13.md":"BYDY6Wqq","works_time-tools_time-tools-14.md":"ClUeIRP5","works_time-tools_time-tools-15.md":"Bo8MgxRH","works_time-tools_time-tools-2.md":"B_IEYB4T","works_time-tools_time-tools-3.md":"Dv6D737n","works_time-tools_time-tools-4.md":"BxCJx03M","works_time-tools_time-tools-5.md":"DQImRmtJ","works_time-tools_time-tools-6.md":"DEwJX9sQ","works_time-tools_time-tools-7.md":"DC7C5-u6","works_time-tools_time-tools-8.md":"BE8JGqo0","works_time-tools_time-tools-9.md":"DaXnyGRr"}
