{"configdoc_show_bole.md":"B1V0knP0","aboutme.md":"BTuhtcI6","ai_stable-diffusion_index.md":"5uUxBj-p","changelog.md":"C2q4W_cp","configdoc_top_address.md":"CZdBLvrd","bigweb_js_apply.md":"DOjH3dOm","bigweb_css_ifc.md":"DpKUbbLp","bigweb_js_module.md":"DvcIhets","ai_coze_juejin-hot-rank-bot.md":"D3vUePu5","bigweb_js_judgearr.md":"qnhhOy9j","bigweb_js_mycall.md":"C3X-hr8E","bigweb_js_p1.md":"DJFygR9Y","bigweb_css_index.md":"DkeK0jUc","bigweb_browser_cache.md":"CMNYgZbY","configdoc_show_whyfe.md":"Q3hMcYi5","bigweb_js_mybind.md":"DGI89O6m","bigweb_js_numnotequal.md":"BAsiZLRy","bigweb_js_scope.md":"ChZgnGgI","bigweb_js_currying.md":"C66Sc8Ba","bigweb_js_blob.md":"BOyD_s4v","bigweb_browser_eventloop.md":"DoSI7azO","configdoc_newyear_2022.md":"C0qchSLu","bigweb_js_runcontext.md":"CSZLHGgQ","bigweb_js_event.md":"CDqBGjx_","bigweb_js_changearr.md":"e3MjjxD1","bigweb_js_scopelink.md":"JiV1c6nN","bigweb_browser_chrome-devtools-study.md":"BSMB5gXh","bigweb_js_asyncawait.md":"B0KB_Sg2","bigweb_js_objdiffprim.md":"pPuok0mJ","bigweb_js_objparam.md":"BDsGATTi","bigweb_js_onload-ready.md":"CmBMMlu-","bigweb_browser_storage.md":"BZqRq_cq","bigweb_js_p0.md":"D96DekQx","bigweb_js_p2.md":"CrbaY-I-","bigweb_css_selectors.md":"CISpqdFG","bigweb_js_ecmathis.md":"BZLQB-LD","bigweb_css_p1.md":"g72pSyWh","bigweb_js_p5.md":"BA3gH6JW","bigweb_css_p2.md":"Ct0LnHkG","bigweb_browser_safe.md":"DaoM4c0o","bigweb_js_index copy.md":"CzA3X6MF","bigweb_html_index.md":"CIpC0ixd","bigweb_js_promise copy.md":"BBmgd_iY","bigweb_bun_bun-shell.md":"B-mQsZla","bigweb_html_semantic.md":"DHK44u-B","bigweb_js_myapply.md":"pfG_H4KW","configdoc_show_sw.md":"B3PcRt5-","configdoc_show_whyfe-2024.md":"DiIIYlfU","bigweb_idea.md":"DYzdd3JX","bigweb_js_p4.md":"C7nXASr2","bigweb_js_instanceof copy.md":"BrGzhcqy","bigweb_css_level.md":"CC9xMdNJ","bigweb_js_arrowfun.md":"NtATfTUr","bigweb_js_delete.md":"B4ggumAj","bigweb_css_box.md":"CUiuvi2d","bigweb_js_primitivetype.md":"IE2KFLR2","bigweb_js_deepclone.md":"Dt7k6uRM","bigweb_js_diff-for-in-of.md":"D8ffKMoT","bigweb_js_index.md":"DFp0Tdqs","bigweb_js_equal.md":"DJdD65Ty","bigweb_js_copy.md":"CbENjJWy","bigweb_js_inherit.md":"CiMd3xHQ","bigweb_js_likearray.md":"DxHygdwb","bigweb_css_pseudo-class.md":"DjJ1GLmx","bigweb_js_prototype.md":"HnkbWv4K","bigweb_js_getelement.md":"Cn75yTYK","configdoc_top_notice.md":"2uRLdaYk","bigweb_js_symbol.md":"CuhJD-SC","bigweb_js_promise.md":"C3YXWwe9","bigweb_js_promiseall.md":"ZHPFTDt9","bigweb_css_flex.md":"CFrlwtYH","bigweb_js_duplicate.md":"Ba64rXdE","bigweb_js_es6_.md":"W0QntFNb","bigweb_browser_block.md":"DGBIUQ7o","bigweb_css_reflow.md":"Ccjez2ww","bigweb_js_closure.md":"Dxjj7q6u","technology_learn_qiniu-imgbed.md":"KeT3XIyg","bigweb_browser_index.md":"B1vzO-cm","bigweb_js_clock.md":"avyeN1PQ","bigweb_browser_render.md":"BGHOSiMY","bigweb_css_pseudo-element.md":"BU_hWeiA","ai_stable-diffusion_mac-install.md":"CtRojpqj","bigweb_js_immed-setinterval.md":"C0GXPRv5","bigweb_js_mynew.md":"BuNlOBbC","bigweb_browser_cors.md":"BL0G5vU-","bigweb_js_p3.md":"Ceg2OOdz","technology_learn_tx-serverless-static.md":"CU4ue8LY","bigweb_performance_lazyload.md":"CdCzKvhv","bigweb_performance_monitor.md":"QzLDZ89j","bigweb_js_judgeobj.md":"CHVOhdA_","technology_study_design-patterns2.md":"BzJQpD8N","bigweb_js_typeof.md":"BgqnMIxF","bigweb_js_valuepass.md":"jPVJMpsy","bigweb_js_async.md":"DF76iz7G","works_time-lover_timelover-1.md":"Bm_oEvcB","bigweb_browser_problem.md":"BuVyjofa","bigweb_performance_cdn.md":"WLnPiTQW","technology_learn_deploy-preview-pr.md":"Bd-EcG-v","technology_learn_ep2-docker.md":"GGMbhZl9","bigweb_js_mergerequest.md":"DfO2hlOc","technology_learn_fixed-page.md":"C3-lm5kc","technology_learn_forof-idx.md":"absj8L9t","bigweb_performance_preload.md":"DmJSKEeh","technology_learn_git-base.md":"Cb_IaKh5","bigweb_js_nullobj.md":"mc0Luekl","bigweb_vue_showif.md":"zC2W4Emi","bigweb_vue_vnode.md":"B5wyNMs-","technology_learn_jpg-compress.md":"BXLXBTBw","bigweb_vueresource_index.md":"BhF78dKj","coding_algorithm_addstring.md":"CwC3kzpg","bigweb_js_variableobject.md":"CvBoqVxp","technology_learn_mergefile.md":"uP9IggDJ","bigweb_js_getbool.md":"CC2NUIwk","technology_learn_jsencrypt.md":"DFknE3_G","coding_algorithm_feibo1.md":"BbtIcuZC","coding_algorithm_feibo2.md":"BQoU0C41","coding_algorithm_headsort.md":"CC1e5Otz","coding_algorithm_index.md":"DKY2ZDJO","computerbase_design_abstractfactory.md":"RSYS_iw4","coding_algorithm_judgesymmetrytree.md":"C4o7hJ3f","coding_algorithm_linkreserve.md":"BxzmbYYV","bigweb_js_instanceof.md":"Crieh4GP","coding_algorithm_publicstring.md":"BJEg7aMS","coding_algorithm_publicstringlen.md":"Bixy97Nf","coding_algorithm_quicksort.md":"IsG1bxWE","coding_algorithm_treeleveltraverse.md":"D233Tyo_","technology_learn_nodejs-getting-started.md":"yJI7xvAt","computerbase_internet_clength.md":"CRlXiAJ7","computerbase_internet_http.md":"DedoDyrI","bigweb_node_standard-node-cli.md":"B3GEkMnP","computerbase_internet_index.md":"A9kxJ2D4","computerbase_internet_tcp-udp.md":"Z_SN83O4","computerbase_internet_tcp.md":"3w7tWuaw","computerbase_internet_udp.md":"CE9HlDkh","computerbase_algorithm_index.md":"l1AtQH_I","computerbase_algorithm_sort.md":"BqrdOall","computerbase_design_factory.md":"Bk7siODj","computerbase_design_index.md":"LYtm6qvE","technology_learn_png-compress.md":"C7DYBCYh","computerbase_leetcode_index.md":"DRCAzZ1l","computerbase_os_communicate.md":"BWMiNiyx","computerbase_os_deadlock.md":"B8fvFoiz","computerbase_os_difprothr.md":"C4ul_PJs","computerbase_os_index.md":"B7eHPXQ7","computerbase_os_process.md":"Boj96Y6p","computerbase_os_thread.md":"C7saMBLJ","essay_dev_2024-blog-perf.md":"RNzRoWmU","group.md":"DCCvK0cs","interview_code_transfer.md":"CDzgTO4D","interview_code_treetraverse.md":"a9JIKQ9V","interview_internet_index.md":"BaJI7QTj","technology_learn_pnpm-issue-githubactions.md":"BrXHg5Cn","interview_mini_differentweb.md":"MqjHmLsW","interview_mini_feature.md":"CFSMWBke","interview_mini_index.md":"CEIa43qs","interview_mini_principle.md":"lvayan9e","interview_offer_index.md":"hE8WR8aQ","interview_offer_p50.md":"Di293jKn","bigweb_js_garbage.md":"Bb4rj5sS","interview_offer_p53-2.md":"69B-dqSZ","bigweb_node_index.md":"qhNlNMlR","interview_offer_p54.md":"C4Gu4Bsz","bigweb_performance_ssr.md":"BZ5roGsX","bigweb_performance_throttling.md":"DFJrHVBg","interview_offer_p55-1.md":"BdmJcpxT","technology_learn_node-require-json.md":"BBYWmRzw","interview_offer_p58.md":"BDmP5qGw","interview_os_index.md":"BdCB1TbJ","interview_other_engineering.md":"_OWnMZsO","interview_other_index.md":"Dbeq22As","interview_other_inputurl.md":"LUEOIyOX","bigweb_regexp_p1.md":"CMr8oUsp","interview_other_judgetype.md":"BGIgsaqO","interview_other_promote.md":"DFcwjE94","technology_learn_upyun.md":"DOSJJ_Ug","interview_other_prototype.md":"BfA2tBkg","interview_performance_firstscreenrender.md":"BC5h_eWj","interview_performance_index.md":"BeDjrc4P","interview_vue_index.md":"3YES59SO","stocks_precisionheadshot_index.md":"BzQSFkvl","stocks_sentimentcore_index.md":"C28uAOb0","technology_learn_array-buffer.md":"C53bqY1G","technology_learn_copy-branch.md":"DnOSKNlI","technology_learn_deepin-wemeet.md":"CjTWLB-S","bigweb_vue_communicate.md":"BS9n6H5K","bigweb_js_throttling.md":"D1QFTYg-","coding_algorithm_mergesort.md":"XfESPxOF","bigweb_vue_compile.md":"DaH-tShO","bigweb_vue_computed.md":"BEDb9Os1","bigweb_vue_dep.md":"C5S97qdU","bigweb_vue_diff.md":"BkXUPM9V","bigweb_vue_extend.md":"zQ93HUVc","bigweb_vue_index.md":"Jaii59qI","bigweb_vue_keep-alive.md":"lYP4xL4m","index.md":"Di0h7rRj","interview_offer_p55.md":"DaZfgaBI","interview_other_object.md":"_iVSF0df","bigweb_js_this.md":"DHiZpRmA","technology_learn_mini-lottie.md":"CZ52xUYD","bigweb_js_equala.md":"DQ5bpmNP","bigweb_js_float.md":"DsJOjxpZ","computerbase_design_single.md":"_pfCOk02","bigweb_node_nvm-iterm.md":"CfRcpL4H","technology_learn_cnnc.md":"BfBRfjbU","bigweb_js_v8garbage.md":"iwpg8Bpj","technology_learn_faas.md":"DQyljg-H","interview_code_index.md":"BvI0_18o","bigweb_performance_image.md":"Cxj2Fjqs","bigweb_vue_mechanism.md":"EFfBM3jE","technology_learn_index.md":"BhVz3bmo","technology_learn_tool-methods.md":"C4sWTAWI","bigweb_js_runstack.md":"BcwjQ_Vq","bigweb_vue_hook.md":"CAKwqAV5","bigweb_vue_mixin.md":"DqMwoGzc","bigweb_performance_prerender.md":"BZ6DxcHV","bigweb_node_mongodb.md":"DYog5-MI","bigweb_performance_index.md":"uwJ-hRi4","bigweb_node_p1.md":"DSJwxJCU","bigweb_performance_internet.md":"Clm1pwfw","bigweb_css_bfc.md":"P_gJtjdk","technology_learn_js-cover.md":"B_ox9BtY","technology_study_index.md":"CIj1iYzP","bigweb_js_eventloop.md":"pPdxvndG","technology_learn_loadenv.md":"CEfKl4_H","technology_learn_vite-plugin-monitor1.md":"CFjAr98Z","technology_learn_vite-plugin-monitor3.md":"C5a4z9P6","technology_learn_vite-react-js.md":"YfjaWZpw","technology_tpl_index.md":"C7SSbqng","technology_tpl_uni-vue3-cli_3.md":"Bt3wBNnN","bigweb_js_closureuse.md":"BoVoBbeZ","technology_learn_webapck2vite2.md":"ndypf025","technology_study_design-patterns0.md":"UYMsDBHk","technology_learn_window-var.md":"BcYk3qRb","bigweb_browser_core.md":"P09-ZrPX","bigweb_es6_index.md":"Cg0nrDOw","technology_learn_yanglegeyang.md":"B6QCsr1D","technology_source_core-decorators-1.md":"BlqqUdcy","bigweb_js_judgedate.md":"BSs7DW72","technology_source_core-decorators-2.md":"g_xz58Gw","technology_source_core-decorators-3.md":"DSRqmC8l","technology_source_file-saver-source.md":"BGAZAmP3","technology_source_index.md":"Czy0145e","technology_works_codenote.md":"BVN0h_tn","technology_source_objectid.md":"BYwXtfDm","technology_study_chrome-debug3.md":"D7qt0VWc","technology_source_vite-loadenv.md":"Dpqdv0BX","technology_works_escheck.md":"C6TJ-yVr","technology_works_share-snippets.md":"BiXdmi-V","technology_learn_mid-autumn-festival.md":"VRwJ-GYK","works_time-tools_time-tools-9.md":"CVtlIvON","works_time-tools_time-tools-8.md":"D4GFUTYj","works_time-tools_time-tools-2.md":"DN7TM2k6","technology_tpl_uni-vue3-cli_2.md":"BoNsZzYc","technology_works_vitepress-plugin-pagefind.md":"ChIaobkp","technology_learn_ux.md":"xEpVs4nt","weekly_index.md":"DdL6jh0k","works_time-lover_index.md":"BAZ5zYdl","works_time-lover_timelover-2.md":"BLB8NqMj","works_time-tools_index.md":"k-eFjfnr","technology_study_design-patterns1.md":"DEtkC7vF","works_time-tools_time-tools-1.md":"BA-H4Rn1","works_time-tools_time-tools-11.md":"DmM4yfr8","works_time-tools_time-tools-10.md":"v_BgaLL8","works_time-tools_time-tools-12.md":"Cw2Ede5C","works_time-tools_time-tools-13.md":"bPOIAbYA","interview_code_debounce-throttle.md":"CuNwcd1N","technology_learn_ssh-no-pwd-login.md":"By2q2xfJ","technology_tpl_vite-vue3-template.md":"57N6fsj4","bigweb_js_typeconvert.md":"CEtR1pCZ","technology_study_chrome-debug1.md":"DMmi5Hwt","works_time-tools_time-tools-3.md":"DMkTjxtK","interview_code_kmp.md":"CpfUqCRT","works_time-tools_time-tools-4.md":"qTu7tnYt","technology_study_chrome-debug4.md":"DgE4_pCk","technology_study_http-proxy-fail.md":"BiHrK7ty","works_time-tools_time-tools-5.md":"D4l57FsF","works_time-tools_time-tools-6.md":"CR0ny6yz","technology_study_chrome-debug5.md":"BHUQxDKP","works_time-tools_time-tools-7.md":"epT4gNll","technology_study_chrome-debug6.md":"BovTZicF","technology_works_theme.md":"Bf8RvEHe","technology_works_ewuit.md":"DMeZqawB","technology_works_node-cli.md":"B3FV8USa","interview_code_myclock.md":"BsRB89MZ","technology_learn_tx-serverless-node.md":"OfM9bX-5","bigweb_js_es6.md":"DacuH5dG","technology_works_snippets.md":"DvaP0Nl8","technology_study_chrome-debug2.md":"Tzhzbo3F","bigweb_vue_routing.md":"CEqK4w3L","technology_tpl_uni-vue3-cli_1.md":"9f1KYGP_","technology_learn_vite-plugin-monitor2.md":"W3bUCDLt","technology_learn_vitepress-plugin-rss.md":"BROIZJNp","bigweb_regexp_index.md":"DpAos8GT","interview_code_middle-center.md":"BDgaTP6y","works_time-tools_time-tools-15.md":"CJE4wdoV","bigweb_node_phantom-dep-cli.md":"Bz9CBhxB","technology_theory_index.md":"CwDkR1_F","technology_works_fs-cli.md":"Bpjkb52s","technology_theory_serverless.md":"BGiVn-WC","bigweb_vue_responsive.md":"Bt5GZdfo","technology_study_nvm-ls-remote.md":"DG5jxSyV","technology_works_html-inline-js-transform.md":"CbNjOsC5","technology_learn_webapck2vite.md":"1ccWxpRE","technology_works_online-resume.md":"wGdVZJ_m","technology_study_ts-decorators.md":"DQGjHQoF","technology_tpl_web-sdk-tpl.md":"CEg37Vc0","technology_learn_qiniu-oss.md":"DSu3jweQ","technology_works_eslint-plugin-todo-ddl.md":"CxJfsdWO","works_time-tools_time-tools-14.md":"BP_2Zs1_","technology_learn_eslint-plugin.md":"BzYByM_y","technology_learn_esm-require.md":"CIzN8b1O","technology_works_sm-cli.md":"CqJTYZaa","bigweb_node_compress-response.md":"DFY-cUnG","bigweb_performance_dnspre.md":"BE7HGf1P","technology_works_index.md":"CELDEQ3c"}
