{"aboutme.md":"DBHtgwvy","ai_coze_juejin-hot-rank-bot.md":"DKyLWven","ai_stable-diffusion_index.md":"C4XnbQBJ","ai_stable-diffusion_mac-install.md":"BLP9NWg6","bigweb_browser_block.md":"DkfWqscD","bigweb_browser_cache.md":"DzmXmclm","bigweb_browser_chrome-devtools-study.md":"C6UZyck3","bigweb_browser_core.md":"BGb5ZyT1","bigweb_browser_cors.md":"eGcQk15Y","bigweb_browser_eventloop.md":"De8JXCdi","bigweb_browser_index.md":"BpyMft0y","bigweb_browser_problem.md":"DfMD0yBj","bigweb_browser_render.md":"D0L2xsmH","bigweb_browser_safe.md":"CIUKFfy8","bigweb_browser_storage.md":"BgNIrRhq","bigweb_bun_bun-shell.md":"DMCYJyHD","bigweb_css_bfc.md":"nyrguu8c","bigweb_css_box.md":"C3Pq-tj_","bigweb_css_flex.md":"B5jcqC0K","bigweb_css_ifc.md":"DzzSNers","bigweb_css_index.md":"qzd4SlrK","bigweb_css_level.md":"YBIBFFz_","bigweb_css_p1.md":"B1CnTByS","bigweb_css_p2.md":"B7BBCSRa","bigweb_css_pseudo-class.md":"DFpCgREv","bigweb_css_pseudo-element.md":"DtPx-RRE","bigweb_css_reflow.md":"KXvEQXba","bigweb_css_selectors.md":"hpw-MR8q","bigweb_es6_index.md":"7_3CyQzI","bigweb_html_index.md":"rISOFeLd","bigweb_html_semantic.md":"mHouXxq1","bigweb_idea.md":"COECqClZ","bigweb_js_apply.md":"CB1abBjb","bigweb_js_arrowfun.md":"BJAmKR34","bigweb_js_async.md":"C0RYwUUX","bigweb_js_asyncawait.md":"zsvv-Ydq","bigweb_js_blob.md":"Cq3iOuTg","bigweb_js_changearr.md":"Qn_ANsWW","bigweb_js_clock.md":"B9uAO5rT","bigweb_js_closure.md":"L3y5G87X","bigweb_js_closureuse.md":"B7c89NKS","bigweb_js_copy.md":"CnDzTVmt","bigweb_js_currying.md":"DNe9i-aP","bigweb_js_deepclone.md":"C0GjCmR4","bigweb_js_delete.md":"BEGzUpHV","bigweb_js_diff-for-in-of.md":"CSCQxqvP","bigweb_js_duplicate.md":"BqKaN_Lv","bigweb_js_ecmathis.md":"rzeqaC4C","bigweb_js_equal.md":"WyUU5MCw","bigweb_js_equala.md":"CsKiDMjB","bigweb_js_es6.md":"BlSDoyZD","bigweb_js_es6_.md":"DIV6wtVH","bigweb_js_event.md":"CcAtQA9z","bigweb_js_eventloop.md":"DZ6MCcoN","bigweb_js_float.md":"BQkso3OF","bigweb_js_garbage.md":"aRWgS51j","bigweb_js_getbool.md":"CUsxAY_f","bigweb_js_getelement.md":"BL6H_7IC","bigweb_js_immed-setinterval.md":"COzVCwFU","bigweb_js_index copy.md":"BRAosBxs","bigweb_js_index.md":"-1SaDAEi","bigweb_js_inherit.md":"24URa75g","bigweb_js_instanceof copy.md":"B8peR8z8","bigweb_js_instanceof.md":"z8AVeds9","bigweb_js_judgearr.md":"wXyIQqqD","bigweb_js_judgedate.md":"DaF4glpz","bigweb_js_judgeobj.md":"4dI1my_Y","bigweb_js_likearray.md":"CswF8Jw9","bigweb_js_mergerequest.md":"DR--8xqm","bigweb_js_module.md":"BRYPfhVx","bigweb_js_myapply.md":"nZYtvTZD","bigweb_js_mybind.md":"vQRVe2WN","bigweb_js_mycall.md":"DJxj-2A_","bigweb_js_mynew.md":"CJNJ3QZ0","bigweb_js_nullobj.md":"CSNlyn1J","bigweb_js_numnotequal.md":"Da7KxF8R","bigweb_js_objdiffprim.md":"Djbwd6dL","bigweb_js_objparam.md":"MGSnggJY","bigweb_js_onload-ready.md":"Dj4W99Yk","bigweb_js_p0.md":"Cyj1e89U","bigweb_js_p1.md":"ghxWEkga","bigweb_js_p2.md":"DShvNtCr","bigweb_js_p3.md":"D9m-NuRZ","bigweb_js_p4.md":"CnB7z_ao","bigweb_js_p5.md":"DTBTAJb1","bigweb_js_primitivetype.md":"BegRgZ9E","bigweb_js_promise copy.md":"Bv7VMu_K","bigweb_js_promise.md":"BIkTEEgi","bigweb_js_promiseall.md":"D7cO9Im7","bigweb_js_prototype.md":"CAqWw_-j","bigweb_js_runcontext.md":"D13IWgmR","bigweb_js_runstack.md":"swFAZXRP","bigweb_js_scope.md":"DamzIp26","bigweb_js_scopelink.md":"DNqghese","bigweb_js_symbol.md":"BFVkyG3F","bigweb_js_this.md":"eS72xLhr","bigweb_js_throttling.md":"CJwvcSlS","bigweb_js_typeconvert.md":"BHB7Tlg4","bigweb_js_typeof.md":"WBlTIKJk","bigweb_js_v8garbage.md":"DlqMjoka","bigweb_js_valuepass.md":"COFkSMV1","bigweb_js_variableobject.md":"D9kYH0lF","bigweb_node_compress-response.md":"BUThcfKe","bigweb_node_index.md":"BtluJbT-","bigweb_node_mongodb.md":"B3HImgoH","bigweb_node_nvm-iterm.md":"BUeYMdXu","bigweb_node_p1.md":"DP7jta5-","bigweb_node_phantom-dep-cli.md":"BLEH8PM-","bigweb_node_standard-node-cli.md":"ByUz8OOy","bigweb_node_前端接口神器之 json-server 详细使用指南 - megasu - 博客园.md":"DaoHasK5","bigweb_performance_cdn.md":"nYZ6Zb8K","bigweb_performance_dnspre.md":"C-np5fGD","bigweb_performance_image.md":"BXsdvRsT","bigweb_performance_index.md":"CcNd0-5U","bigweb_performance_internet.md":"h7Ee4vND","bigweb_performance_lazyload.md":"DJ029riL","bigweb_performance_monitor.md":"LLTPwDOF","bigweb_performance_preload.md":"BVMiFsqc","bigweb_performance_prerender.md":"X-8dbWaR","bigweb_performance_ssr.md":"CMsBA26I","bigweb_performance_throttling.md":"BAL19gxx","bigweb_regexp_index.md":"DmfjezfT","bigweb_regexp_p1.md":"B6qsSyaT","bigweb_vue_communicate.md":"B4chpTMZ","bigweb_vue_compile.md":"DVHCFeS2","bigweb_vue_computed.md":"CiqxTkxa","bigweb_vue_dep.md":"BRAO2PWs","bigweb_vue_diff.md":"DSnQb1JE","bigweb_vue_extend.md":"DM1ZBVih","bigweb_vue_hook.md":"DLFISEO4","bigweb_vue_index.md":"Chtb64q8","bigweb_vue_keep-alive.md":"qT_CmFD8","bigweb_vue_mechanism.md":"1ZOWk6Ir","bigweb_vue_mixin.md":"vYFDioRe","bigweb_vue_responsive.md":"CzoVtOp0","bigweb_vue_routing.md":"BXWjzSO7","bigweb_vue_showif.md":"UrDYQVTd","bigweb_vue_vnode.md":"BtOtQEUa","bigweb_vueresource_index.md":"2gJaJv04","changelog.md":"DuVXYqWr","coding_algorithm_addstring.md":"CVzWq53a","coding_algorithm_feibo1.md":"BumpNNlE","coding_algorithm_feibo2.md":"CFQfL6uZ","coding_algorithm_headsort.md":"CVL-yPDJ","coding_algorithm_index.md":"CP7VajRM","coding_algorithm_judgesymmetrytree.md":"qdnz-IAS","coding_algorithm_linkreserve.md":"CIQfbBAT","coding_algorithm_mergesort.md":"BIht_Z5S","coding_algorithm_publicstring.md":"DfQw9XmB","coding_algorithm_publicstringlen.md":"Cm9yKbAk","coding_algorithm_quicksort.md":"-ga025D-","coding_algorithm_treeleveltraverse.md":"Ta4fecMK","coding_github_git删除当前分支下的所有历史版本与log并同步至github_git如何清除历史版本.md":"CsLoGnm6","coding_github_index.md":"DVdlVPw5","computerbase_algorithm_index.md":"CHUVyKml","computerbase_algorithm_sort.md":"C-16yHr0","computerbase_design_abstractfactory.md":"BU6iIO3o","computerbase_design_factory.md":"DfAEoMh6","computerbase_design_index.md":"Q25IUOjm","computerbase_design_single.md":"BY9_LIr6","computerbase_internet_clength.md":"2R6u0Ybk","computerbase_internet_http.md":"D-LUfXnG","computerbase_internet_index.md":"arxyhjYM","computerbase_internet_tcp-udp.md":"CuP26TU8","computerbase_internet_tcp.md":"Dxvw3aMh","computerbase_internet_udp.md":"tF2uhzuT","computerbase_leetcode_index.md":"B0xhiLPM","computerbase_os_communicate.md":"CiXiv7O8","computerbase_os_deadlock.md":"CZg0c6tS","computerbase_os_difprothr.md":"o9ZkE1ES","computerbase_os_index.md":"BLMu1AEr","computerbase_os_process.md":"Dm3FqJM-","computerbase_os_thread.md":"KYwpYCgJ","configdoc_newyear_2022.md":"BHz5gRMz","configdoc_show_bole.md":"C8CdAXZa","configdoc_show_sw.md":"BuORM1nG","configdoc_show_whyfe-2024.md":"r-qE77iU","configdoc_show_whyfe.md":"COcho7ai","configdoc_top_address.md":"DRb3KlBq","configdoc_top_notice.md":"C6dMkjMa","essay_dev_2024-blog-perf.md":"BErdN5Tg","group.md":"LGQAwqiN","index.md":"DkTNWpH-","interview_code_debounce-throttle.md":"C8Z7aPTl","interview_code_index.md":"BTtEbaKU","interview_code_kmp.md":"BM3gWEUb","interview_code_middle-center.md":"lIS0xpeu","interview_code_myclock.md":"BEhFDJlR","interview_code_transfer.md":"DiSnxUP8","interview_code_treetraverse.md":"Ct-YykjM","interview_internet_index.md":"CZYh1hd8","interview_mini_differentweb.md":"D0-82Kk7","interview_mini_feature.md":"CPXAvTu8","interview_mini_index.md":"BlJrUbYt","interview_mini_principle.md":"Byj9-FRt","interview_offer_index.md":"Bqs3rEK7","interview_offer_p50.md":"VM3Bnrsp","interview_offer_p53-2.md":"FfcfvBPk","interview_offer_p54.md":"Ch-21Qjm","interview_offer_p55-1.md":"L76Y_117","interview_offer_p55.md":"MxRoNLJZ","interview_offer_p58.md":"NhCqOD6o","interview_os_index.md":"DRyOIFE4","interview_other_engineering.md":"DxV6jsYw","interview_other_index.md":"DEO_IiFM","interview_other_inputurl.md":"xP2t6plC","interview_other_judgetype.md":"CSSpWpR_","interview_other_object.md":"_BOQhWJ8","interview_other_promote.md":"oUOjh1rC","interview_other_prototype.md":"CHNNYMyM","interview_performance_firstscreenrender.md":"BND9c1It","interview_performance_index.md":"C_RVl3zq","interview_vue_index.md":"DYo3Qw-K","stocks_precisionheadshot_index.md":"B5wKLEPY","stocks_sentimentcore_index.md":"CVizYnLs","technology_learn_array-buffer.md":"C8djdrsR","technology_learn_cnnc.md":"hgH27LQO","technology_learn_copy-branch.md":"6WhNb0oU","technology_learn_deepin-wemeet.md":"Cb5SAkT9","technology_learn_deploy-preview-pr.md":"CU7_GZM5","technology_learn_ep2-docker.md":"DRXDL_yM","technology_learn_eslint-plugin.md":"DBZ2_u4l","technology_learn_esm-require.md":"Cvt2sdWU","technology_learn_faas.md":"C9cT5T51","technology_learn_fixed-page.md":"g_GgiOp1","technology_learn_forof-idx.md":"DJ84UhJq","technology_learn_git-base.md":"j4RnzJWJ","technology_learn_index.md":"Dmq91vt2","technology_learn_jpg-compress.md":"CvtRqHMr","technology_learn_js-cover.md":"C3uNChB1","technology_learn_jsencrypt.md":"BbLhlyzl","technology_learn_loadenv.md":"RDQQl_0t","technology_learn_mergefile.md":"_APBmFEe","technology_learn_mid-autumn-festival.md":"DAe2fjAP","technology_learn_mini-lottie.md":"DchyxNlH","technology_learn_node-require-json.md":"haoACbQy","technology_learn_nodejs-getting-started.md":"BszCdOFP","technology_learn_png-compress.md":"CikWhl21","technology_learn_pnpm-issue-githubactions.md":"Bxoz3n4Q","technology_learn_qiniu-imgbed.md":"DX4MT0kx","technology_learn_qiniu-oss.md":"Caw5dbU5","technology_learn_ssh-no-pwd-login.md":"BxmJkvqy","technology_learn_tool-methods.md":"CYTSJCfy","technology_learn_tx-serverless-node.md":"WV7qe-OS","technology_learn_tx-serverless-static.md":"COQ59YKH","technology_learn_upyun.md":"CjTtdv9S","technology_learn_ux.md":"AjTRt8ej","technology_learn_vite-plugin-monitor1.md":"rNdcdMdU","technology_learn_vite-plugin-monitor2.md":"DlcLemek","technology_learn_vite-plugin-monitor3.md":"BJHvrX4X","technology_learn_vite-react-js.md":"CGC8RQd1","technology_learn_vitepress-plugin-rss.md":"DArLx-2e","technology_learn_webapck2vite.md":"D9zsRih2","technology_learn_webapck2vite2.md":"CdKP8HHZ","technology_learn_window-var.md":"DsNiWXKp","technology_learn_yanglegeyang.md":"CHfCrSLM","technology_source_core-decorators-1.md":"CBkU-Vyi","technology_source_core-decorators-2.md":"BoYDpyZ7","technology_source_core-decorators-3.md":"bJ2EzSiI","technology_source_file-saver-source.md":"BHGBPE2m","technology_source_index.md":"D4cYUfAE","technology_source_objectid.md":"DCI0S0k-","technology_source_vite-loadenv.md":"VOgD5eVr","technology_study_chrome-debug1.md":"B1PnCnzw","technology_study_chrome-debug2.md":"CM6NsH8p","technology_study_chrome-debug3.md":"DAAgGn3c","technology_study_chrome-debug4.md":"oDPXVC0m","technology_study_chrome-debug5.md":"CyrLLiIh","technology_study_chrome-debug6.md":"DhaX8na4","technology_study_design-patterns0.md":"DGDYVW4F","technology_study_design-patterns1.md":"CLfCzpap","technology_study_design-patterns2.md":"DVL294KO","technology_study_http-proxy-fail.md":"DZ9lf0xM","technology_study_index.md":"CIj0S_5x","technology_study_nvm-ls-remote.md":"Cv7r3lon","technology_study_ts-decorators.md":"BDy5Qykd","technology_theory_index.md":"CHAcFulu","technology_theory_serverless.md":"Bk-4Np5p","technology_tpl_index.md":"prihZc-z","technology_tpl_uni-vue3-cli_1.md":"a_RgNUOX","technology_tpl_uni-vue3-cli_2.md":"CdSGiqk1","technology_tpl_uni-vue3-cli_3.md":"lW1IRu3w","technology_tpl_vite-vue3-template.md":"0gKIF-D-","technology_tpl_web-sdk-tpl.md":"CNeH0Dzt","technology_works_codenote.md":"tC0O9Riy","technology_works_escheck.md":"wwMB4ZgO","technology_works_eslint-plugin-todo-ddl.md":"RrkGpwiZ","technology_works_ewuit.md":"CR_xlfsm","technology_works_fs-cli.md":"CfnqpVor","technology_works_html-inline-js-transform.md":"hEBO6p3n","technology_works_index.md":"Dhszf52M","technology_works_node-cli.md":"DUhwZr0N","technology_works_online-resume.md":"CeU7wV5I","technology_works_share-snippets.md":"H1JNXMNY","technology_works_sm-cli.md":"iJSezk1A","technology_works_snippets.md":"DCT3GOsv","technology_works_theme.md":"BgJ4aT73","technology_works_vitepress-plugin-pagefind.md":"Dyt74Obo","weekly_index.md":"Me6zg-xe","works_time-lover_index.md":"CwSkpGFZ","works_time-lover_timelover-1.md":"U32y24nS","works_time-lover_timelover-2.md":"7VrnjmkV","works_time-tools_index.md":"BUAzVE9S","works_time-tools_time-tools-1.md":"DREty3sI","works_time-tools_time-tools-10.md":"B_0LZ552","works_time-tools_time-tools-11.md":"Bc6ALpHA","works_time-tools_time-tools-12.md":"BJNMTk-k","works_time-tools_time-tools-13.md":"BfdFnu0r","works_time-tools_time-tools-14.md":"BPtP5h61","works_time-tools_time-tools-15.md":"DtckS8yB","works_time-tools_time-tools-2.md":"DMuJHkb9","works_time-tools_time-tools-3.md":"CtEkwi84","works_time-tools_time-tools-4.md":"ZPoD_56T","works_time-tools_time-tools-5.md":"Ca2l6HcQ","works_time-tools_time-tools-6.md":"D6Z5G-s_","works_time-tools_time-tools-7.md":"BAgpFJfY","works_time-tools_time-tools-8.md":"Bbdfu0jD","works_time-tools_time-tools-9.md":"CZXd14JX"}
