{"aboutme.md":"DuMkUqC-","ai_coze_juejin-hot-rank-bot.md":"ISxjg7At","ai_stable-diffusion_index.md":"Dka3sZ1Y","ai_stable-diffusion_mac-install.md":"DozaSkG4","bigweb_browser_block.md":"CujMHBtt","bigweb_browser_cache.md":"DDI9kdYG","bigweb_browser_chrome-devtools-study.md":"D4gccKZH","bigweb_browser_core.md":"BwJMhrRV","bigweb_browser_cors.md":"C0LnNNnP","bigweb_browser_eventloop.md":"C6Eg3g1h","bigweb_browser_index.md":"C-uERPAl","bigweb_browser_problem.md":"BzDen9BV","bigweb_browser_render.md":"uWnXcCeR","bigweb_browser_safe.md":"DArmQxxw","bigweb_browser_storage.md":"DLsn0Owo","bigweb_bun_bun-shell.md":"BNjTUGWd","bigweb_css_bfc.md":"Cx-ChAnI","bigweb_css_box.md":"D5qHnFTf","bigweb_css_flex.md":"DJQQlLvV","bigweb_css_ifc.md":"DYffwwPu","bigweb_css_index.md":"D8HzYIqu","bigweb_css_level.md":"Tybl9Zsg","bigweb_css_p1.md":"CmoFJLO8","bigweb_css_p2.md":"DDAV8ARi","bigweb_css_pseudo-class.md":"CiQ-Jm90","bigweb_css_pseudo-element.md":"DxKDXw8E","bigweb_css_reflow.md":"BtNv05BN","bigweb_css_selectors.md":"TOMbas3E","bigweb_es6_index.md":"DvjXJ25w","bigweb_html_index.md":"D_7RFyJ0","bigweb_html_semantic.md":"DtDubmFE","bigweb_idea.md":"Brm9aPyZ","bigweb_js_apply.md":"Da4M0rIE","bigweb_js_arrowfun.md":"BPFyPvsl","bigweb_js_async.md":"BxhO2YWb","bigweb_js_asyncawait.md":"DURTRn-Y","bigweb_js_blob.md":"CaFQNCW-","bigweb_js_changearr.md":"BUu2RyLy","bigweb_js_clock.md":"D9uSmVOe","bigweb_js_closure.md":"CZPz0av9","bigweb_js_closureuse.md":"apJ-UTS-","bigweb_js_copy.md":"BZ_Ekn9v","bigweb_js_currying.md":"-Mrn_Nld","bigweb_js_deepclone.md":"DBFstlpF","bigweb_js_delete.md":"D4Pveaox","bigweb_js_diff-for-in-of.md":"BbiV1BaJ","bigweb_js_duplicate.md":"CABsBq4d","bigweb_js_ecmathis.md":"k3XB-kqS","bigweb_js_equal.md":"BK6xQPpA","bigweb_js_equala.md":"mVEfAEsB","bigweb_js_es6.md":"Klb1GBRQ","bigweb_js_es6_.md":"CrpbihVV","bigweb_js_event.md":"BIS8d6BQ","bigweb_js_eventloop.md":"B0iSKOPU","bigweb_js_float.md":"tNTtIzzO","bigweb_js_garbage.md":"XQuWTV5X","bigweb_js_getbool.md":"DJVl16vf","bigweb_js_getelement.md":"DlnETttC","bigweb_js_immed-setinterval.md":"Bi5hYsCq","bigweb_js_index copy.md":"CgMX75VS","bigweb_js_index.md":"BBfVHmYi","bigweb_js_inherit.md":"BTeoplBn","bigweb_js_instanceof copy.md":"Ch53DtuD","bigweb_js_instanceof.md":"DaIb7Nvx","bigweb_js_judgearr.md":"DUfjODHi","bigweb_js_judgedate.md":"BeSwuQx8","bigweb_js_judgeobj.md":"D1wM4El4","bigweb_js_likearray.md":"CO3H9lrn","bigweb_js_mergerequest.md":"CjSh7CSy","bigweb_js_module.md":"Cgd5_6o_","bigweb_js_myapply.md":"D9sXR80Z","bigweb_js_mybind.md":"CSV3Ieb6","bigweb_js_mycall.md":"B51D49HQ","bigweb_js_mynew.md":"B2pUOMOT","bigweb_js_nullobj.md":"C4E3FizA","bigweb_js_numnotequal.md":"bHvVO4fr","bigweb_js_objdiffprim.md":"B4AQb3O5","bigweb_js_objparam.md":"CL2YSZKq","bigweb_js_onload-ready.md":"DrSEYYdk","bigweb_js_p0.md":"B6j8FcR5","bigweb_js_p1.md":"kMzTtdeW","bigweb_js_p2.md":"BBHsqCKa","bigweb_js_p3.md":"Bf26lcYp","bigweb_js_p4.md":"DABTG0Ia","bigweb_js_p5.md":"CsFGwLGS","bigweb_js_primitivetype.md":"Bx8vEIqd","bigweb_js_promise copy.md":"CgjzLvPs","bigweb_js_promise.md":"BL7gSQh4","bigweb_js_promiseall.md":"wsVDyy8r","bigweb_js_prototype.md":"D0d5iYlu","bigweb_js_runcontext.md":"DFQwYIKe","bigweb_js_runstack.md":"CULXzxbb","bigweb_js_scope.md":"BOG04Yjh","bigweb_js_scopelink.md":"DJWd4cxR","bigweb_js_symbol.md":"C02M0Qpy","bigweb_js_this.md":"CZGRUqyW","bigweb_js_throttling.md":"DnOR_Kc9","bigweb_js_typeconvert.md":"AxTeLNTs","bigweb_js_typeof.md":"DRL3-ErA","bigweb_js_v8garbage.md":"CqFFKppV","bigweb_js_valuepass.md":"UVrrqnkE","bigweb_js_variableobject.md":"D0Pp3iUG","bigweb_node_compress-response.md":"BI6fCQrH","bigweb_node_index.md":"MW2FNEo-","bigweb_node_mongodb.md":"DFAr31TE","bigweb_node_nvm-iterm.md":"B0QHMKTW","bigweb_node_p1.md":"Bgbg5O_p","bigweb_node_phantom-dep-cli.md":"DAPB_ZUI","bigweb_node_standard-node-cli.md":"D0uI5uc3","bigweb_node_前端接口神器之 json-server 详细使用指南 - megasu - 博客园.md":"kf1y3ag1","bigweb_performance_cdn.md":"ybOOaoIx","bigweb_performance_dnspre.md":"BhE1ka5Y","bigweb_performance_image.md":"Bsmt1hda","bigweb_performance_index.md":"ABzs9gNo","bigweb_performance_internet.md":"Dg0JndWN","bigweb_performance_lazyload.md":"CUdYyDxa","bigweb_performance_monitor.md":"C6ob6sxI","bigweb_performance_preload.md":"C9zyylWn","bigweb_performance_prerender.md":"BBdTebod","bigweb_performance_ssr.md":"mNqg-4DE","bigweb_performance_throttling.md":"BlEVcq2F","bigweb_regexp_index.md":"W0B43Mt3","bigweb_regexp_p1.md":"DvIBpViN","bigweb_vue_communicate.md":"R2ld8T5F","bigweb_vue_compile.md":"IgRftnge","bigweb_vue_computed.md":"Dq8HFeRB","bigweb_vue_dep.md":"C0JsRnGS","bigweb_vue_diff.md":"DqFDoMTP","bigweb_vue_extend.md":"BBOQog64","bigweb_vue_hook.md":"Bn4U2wz0","bigweb_vue_index.md":"ChoHMR7K","bigweb_vue_keep-alive.md":"CzT8g-J9","bigweb_vue_mechanism.md":"tRde1iCv","bigweb_vue_mixin.md":"BbnRYMvk","bigweb_vue_responsive.md":"CljeP0dM","bigweb_vue_routing.md":"Bl5q3Cib","bigweb_vue_showif.md":"DslLDe3s","bigweb_vue_vnode.md":"BuKsH6hQ","bigweb_vueresource_index.md":"CIAHWWkx","coding_algorithm_addstring.md":"DpSPwBRc","coding_algorithm_feibo1.md":"JBPe4vEl","coding_algorithm_feibo2.md":"o2IgRKna","coding_algorithm_headsort.md":"7rMOY8ep","coding_algorithm_index.md":"oG5Q3lFZ","coding_algorithm_judgesymmetrytree.md":"Bhm0XEpJ","coding_algorithm_linkreserve.md":"B4G8Rbga","coding_algorithm_mergesort.md":"BAophzMh","coding_algorithm_publicstring.md":"DtzqtPjJ","coding_algorithm_publicstringlen.md":"BwXUrZJH","coding_algorithm_quicksort.md":"IcjSze2b","coding_algorithm_treeleveltraverse.md":"B7LbAKuD","coding_dotnet_dotnetviavscode.md":"CBy91GXv","coding_dotnet_index.md":"yJluMp07","coding_github_git删除当前分支下的所有历史版本与log并同步至github_git如何清除历史版本.md":"Co61Ha3U","coding_github_index.md":"DMEz9qzI","coding_github_sourcetree ssh密钥缓存问题解决.md":"C1q97m44","computerbase_algorithm_index.md":"CZvBfLXe","computerbase_algorithm_sort.md":"CNjG_G7w","computerbase_design_abstractfactory.md":"-3eEg8kg","computerbase_design_factory.md":"CHlxomO1","computerbase_design_index.md":"Dwn9KChk","computerbase_design_single.md":"DVn-IDZe","computerbase_internet_clength.md":"BIAYaZG1","computerbase_internet_http.md":"Dse22inZ","computerbase_internet_index.md":"mVN9672a","computerbase_internet_tcp-udp.md":"CNCRBv28","computerbase_internet_tcp.md":"CVc4BEMx","computerbase_internet_udp.md":"B0ABtobW","computerbase_leetcode_index.md":"rjov6Kyw","computerbase_os_communicate.md":"Zsmy6sYe","computerbase_os_deadlock.md":"B4QxGHZQ","computerbase_os_difprothr.md":"BmLzTPiv","computerbase_os_index.md":"DkrRypbx","computerbase_os_process.md":"CmtKk_Ig","computerbase_os_thread.md":"D8mI_n7L","configdoc_newyear_2022.md":"CBxz1qSa","configdoc_show_bole.md":"C9YhR_DF","configdoc_show_sw.md":"w4RtXlqA","configdoc_show_whyfe-2024.md":"BwFX2GOs","configdoc_show_whyfe.md":"CVhK52zG","configdoc_top_address.md":"Dv9_tVth","configdoc_top_campusproblem.md":"DQ4qhMeq","configdoc_top_notice.md":"BA2mnJ_3","essay_dev_2024-blog-perf.md":"BjxX2S0-","group.md":"DOyJqwnu","index.md":"Cwr12zn_","interview_code_debounce-throttle.md":"Bc_MuIRv","interview_code_index.md":"n54wHLMD","interview_code_kmp.md":"C5C1pbNW","interview_code_middle-center.md":"BCTHZlYl","interview_code_myclock.md":"BrvXbfQV","interview_code_transfer.md":"BibNCNqm","interview_code_treetraverse.md":"NUhyqVnc","interview_internet_index.md":"B9ssDG7D","interview_mini_differentweb.md":"CsvaUtkc","interview_mini_feature.md":"Dsmls7W4","interview_mini_index.md":"DAyXBnvF","interview_mini_principle.md":"O6NrlULQ","interview_offer_index.md":"BSmqTWvA","interview_offer_p50.md":"J0MnHUWE","interview_offer_p53-2.md":"J33ED8PL","interview_offer_p54.md":"DnJDeICf","interview_offer_p55-1.md":"Dv8e2ag3","interview_offer_p55.md":"zfqzn38a","interview_offer_p58.md":"C9GsCsn_","interview_os_index.md":"0CF7eR4p","interview_other_engineering.md":"IHvrHKcz","interview_other_index.md":"BLMwYD-W","interview_other_inputurl.md":"CMoUH4ju","interview_other_judgetype.md":"1-zJdqoh","interview_other_object.md":"Do2p6dht","interview_other_promote.md":"BYI7RZmG","interview_other_prototype.md":"v9I-LrLW","interview_performance_firstscreenrender.md":"Bfgi-_w9","interview_performance_index.md":"CD4AbFDb","interview_vue_index.md":"Cgxo70aB","stocks_precisionheadshot_index.md":"B6xYhrN1","stocks_sentimentcore_index.md":"CaAdVS8D","technology_learn_array-buffer.md":"Bzuiq6Pz","technology_learn_cnnc.md":"bjoj156F","technology_learn_copy-branch.md":"Dg04FuaO","technology_learn_deepin-wemeet.md":"Oef3lybc","technology_learn_deploy-preview-pr.md":"Cvcs4Rg-","technology_learn_ep2-docker.md":"De0GG4If","technology_learn_eslint-plugin.md":"DYhuqXpS","technology_learn_esm-require.md":"IbPDusGK","technology_learn_faas.md":"CWFevqii","technology_learn_fixed-page.md":"vRDBYlE4","technology_learn_forof-idx.md":"DXVWnXgZ","technology_learn_git-base.md":"CEt-KUjk","technology_learn_index.md":"n-aKN56S","technology_learn_jpg-compress.md":"Dd0JIga5","technology_learn_js-cover.md":"qXBOfgxI","technology_learn_jsencrypt.md":"DKY6W2aS","technology_learn_loadenv.md":"qTpsTDQ5","technology_learn_mergefile.md":"3utwKrSn","technology_learn_mid-autumn-festival.md":"CCQlKQmv","technology_learn_mini-lottie.md":"B2wq6FI-","technology_learn_node-require-json.md":"CYGxuvjl","technology_learn_nodejs-getting-started.md":"DLeZ6Mtf","technology_learn_png-compress.md":"CPCSBZsq","technology_learn_pnpm-issue-githubactions.md":"CP3IdoUD","technology_learn_qiniu-imgbed.md":"BoGHKkwV","technology_learn_qiniu-oss.md":"BUJF__MU","technology_learn_ssh-no-pwd-login.md":"C48p7IKT","technology_learn_tool-methods.md":"DT7B6DCm","technology_learn_tx-serverless-node.md":"ihYTlfr0","technology_learn_tx-serverless-static.md":"CRU00Idi","technology_learn_upyun.md":"BrV33kdH","technology_learn_ux.md":"BKzOiQyS","technology_learn_vite-plugin-monitor1.md":"B48nS4bJ","technology_learn_vite-plugin-monitor2.md":"DseBG5zK","technology_learn_vite-plugin-monitor3.md":"DJzOtQwu","technology_learn_vite-react-js.md":"B4nxO5XI","technology_learn_vitepress-plugin-rss.md":"JEm-7WbD","technology_learn_webapck2vite.md":"WpPCxr0g","technology_learn_webapck2vite2.md":"DKsZ1Dg-","technology_learn_window-var.md":"DLfJp_Dk","technology_learn_yanglegeyang.md":"D2P2mWQC","technology_source_core-decorators-1.md":"DrXspo0E","technology_source_core-decorators-2.md":"BC9vpC-4","technology_source_core-decorators-3.md":"CtkyhduJ","technology_source_file-saver-source.md":"BV6NfQ-m","technology_source_index.md":"KELzt4yT","technology_source_objectid.md":"DkR1xImF","technology_source_vite-loadenv.md":"BPRNPjW1","technology_study_chrome-debug1.md":"DhuwXQKI","technology_study_chrome-debug2.md":"6twjAeZF","technology_study_chrome-debug3.md":"1qoaHVVr","technology_study_chrome-debug4.md":"BcmrBGP_","technology_study_chrome-debug5.md":"CLPXnCll","technology_study_chrome-debug6.md":"DYE7N-_P","technology_study_design-patterns0.md":"m6u6YKeX","technology_study_design-patterns1.md":"BmbhHSv7","technology_study_design-patterns2.md":"Rq2fsCqc","technology_study_http-proxy-fail.md":"CeqHTMcG","technology_study_index.md":"TQBewjWH","technology_study_nvm-ls-remote.md":"EVsswHn_","technology_study_ts-decorators.md":"CjXUXupT","technology_theory_index.md":"BagKYUC2","technology_theory_serverless.md":"CTUSmjQY","technology_tpl_index.md":"0Ei8pcG2","technology_tpl_uni-vue3-cli_1.md":"CtjiIBFY","technology_tpl_uni-vue3-cli_2.md":"CUvLwDFA","technology_tpl_uni-vue3-cli_3.md":"Dvb1YXoC","technology_tpl_vite-vue3-template.md":"WyuPs9qj","technology_tpl_web-sdk-tpl.md":"CJ-z7Aq6","technology_works_codenote.md":"DF5Tm0OJ","technology_works_escheck.md":"CiDyilZp","technology_works_eslint-plugin-todo-ddl.md":"CCdTCuDp","technology_works_ewuit.md":"CGlHHQp3","technology_works_fs-cli.md":"D5ODaFfq","technology_works_html-inline-js-transform.md":"uGuJpWXF","technology_works_index.md":"ByQhQbZQ","technology_works_node-cli.md":"B0EKs4fM","technology_works_online-resume.md":"CDt91wqD","technology_works_share-snippets.md":"BRbDWmb_","technology_works_sm-cli.md":"C2u2fsG3","technology_works_snippets.md":"BYKpsItF","technology_works_theme.md":"D1pLdSBH","technology_works_vitepress-plugin-pagefind.md":"D93pOIcc","weekly_index.md":"CA5YtXrG","works_time-lover_index.md":"qZcAb4bo","works_time-lover_timelover-1.md":"DfAbvqhB","works_time-lover_timelover-2.md":"Dc_W_Tt3","works_time-tools_index.md":"BYjQRJx6","works_time-tools_time-tools-1.md":"BVlh55fJ","works_time-tools_time-tools-10.md":"09fp6Sb4","works_time-tools_time-tools-11.md":"Q43t7DMI","works_time-tools_time-tools-12.md":"BRXOPzEN","works_time-tools_time-tools-13.md":"DENu3O5g","works_time-tools_time-tools-14.md":"COHrLSV2","works_time-tools_time-tools-15.md":"Ce-MoffS","works_time-tools_time-tools-2.md":"BChx59Kr","works_time-tools_time-tools-3.md":"BbZsrdER","works_time-tools_time-tools-4.md":"DHTkSRa5","works_time-tools_time-tools-5.md":"W8_QL-7M","works_time-tools_time-tools-6.md":"BwO9u-ZG","works_time-tools_time-tools-7.md":"BYfwiDy8","works_time-tools_time-tools-8.md":"LN4y_-4k","works_time-tools_time-tools-9.md":"CJQTqoGu"}
