{"aboutme.md":"Bg892HEy","ai_coze_juejin-hot-rank-bot.md":"D1UcezSQ","ai_stable-diffusion_index.md":"DLAqDwuX","ai_stable-diffusion_mac-install.md":"DqMts6m0","bigweb_browser_block.md":"DSJdAEHb","bigweb_browser_cache.md":"B7_PDRS_","bigweb_browser_chrome-devtools-study.md":"Bo8snq-p","bigweb_browser_core.md":"DgGbaYxd","bigweb_browser_cors.md":"r8UgedYP","bigweb_browser_eventloop.md":"BWeulVGV","bigweb_browser_index.md":"BkaseKsL","bigweb_browser_problem.md":"BHHzdxQM","bigweb_browser_render.md":"DuSBE9r-","bigweb_browser_safe.md":"mYHvrt56","bigweb_browser_storage.md":"CMPQzRrf","bigweb_bun_bun-shell.md":"DWvc0_IQ","bigweb_css_bfc.md":"CR0hW2fq","bigweb_css_box.md":"Bk_H3e5E","bigweb_css_flex.md":"DVpvHKC7","bigweb_css_ifc.md":"BA_Wldzj","bigweb_css_index.md":"DwchUM3V","bigweb_css_level.md":"CtIG7Hyl","bigweb_css_p1.md":"v1zz8R7k","bigweb_css_p2.md":"DRgouHVi","bigweb_css_pseudo-class.md":"BzUWkp1m","bigweb_css_pseudo-element.md":"CiSEK84a","bigweb_css_reflow.md":"dSVleuVD","bigweb_css_selectors.md":"D2V3h3nl","bigweb_es6_index.md":"D2lUq07N","bigweb_html_index.md":"DPmza5OR","bigweb_html_semantic.md":"_fwPE6-V","bigweb_idea.md":"B7GQ1Zpl","bigweb_js_apply.md":"By9Wq52N","bigweb_js_arrowfun.md":"DwZLdtJh","bigweb_js_async.md":"Ct_LiF6a","bigweb_js_asyncawait.md":"pb9makB_","bigweb_js_blob.md":"CWQOaRZm","bigweb_js_changearr.md":"CoQ8_xM-","bigweb_js_clock.md":"B3pyKvvo","bigweb_js_closure.md":"BYugV4Fv","bigweb_js_closureuse.md":"CHNBWJpK","bigweb_js_copy.md":"BFDpJh-f","bigweb_js_currying.md":"CqHE7Hv2","bigweb_js_deepclone.md":"Dhyzr6wL","bigweb_js_delete.md":"BzP_Zzh3","bigweb_js_diff-for-in-of.md":"0T68APQ5","bigweb_js_duplicate.md":"Cd56piYv","bigweb_js_ecmathis.md":"VEgN-aAU","bigweb_js_equal.md":"H5gKjaJ7","bigweb_js_equala.md":"D7kysvXv","bigweb_js_es6.md":"C_cgEZ00","bigweb_js_es6_.md":"6hQoTh65","bigweb_js_event.md":"B84BOnjG","bigweb_js_eventloop.md":"DON_0j3P","bigweb_js_float.md":"HT8nWX9O","bigweb_js_garbage.md":"Dnu5n1GF","bigweb_js_getbool.md":"BzleRUz0","bigweb_js_getelement.md":"BW6N1e-B","bigweb_js_immed-setinterval.md":"C9Fzji0E","bigweb_js_index copy.md":"DRkC1U5f","bigweb_js_index.md":"BMWuDiuE","bigweb_js_inherit.md":"C0KM9h-n","bigweb_js_instanceof copy.md":"WyAT_WyE","bigweb_js_instanceof.md":"BSfM02dX","bigweb_js_judgearr.md":"BOuMmu7_","bigweb_js_judgedate.md":"WaW22tCe","bigweb_js_judgeobj.md":"Bg3JdSM3","bigweb_js_likearray.md":"BjCPf_gE","bigweb_js_mergerequest.md":"CwShI3PN","bigweb_js_module.md":"DjvDVNJ-","bigweb_js_myapply.md":"BFaSQqub","bigweb_js_mybind.md":"2aQZ8jSe","bigweb_js_mycall.md":"BDlC9Z7G","bigweb_js_mynew.md":"5g-A06Ba","bigweb_js_nullobj.md":"_QB8pdPJ","bigweb_js_numnotequal.md":"CYK42sDB","bigweb_js_objdiffprim.md":"BL9mvMT-","bigweb_js_objparam.md":"CHmxrZ8L","bigweb_js_onload-ready.md":"Cr4J6u2J","bigweb_js_p0.md":"BluZ6DXy","bigweb_js_p1.md":"CuVemcPh","bigweb_js_p2.md":"CSTHxUqJ","bigweb_js_p3.md":"CPS32-rP","bigweb_js_p4.md":"DGRh4IKR","bigweb_js_p5.md":"c-mz2VFx","bigweb_js_primitivetype.md":"DUbDOzpf","bigweb_js_promise copy.md":"DUEFAN05","bigweb_js_promise.md":"Do1zMMxj","bigweb_js_promiseall.md":"zxe1sGoZ","bigweb_js_prototype.md":"m-Tb7iKp","bigweb_js_runcontext.md":"C1uwNHGJ","bigweb_js_runstack.md":"77he38uF","bigweb_js_scope.md":"DIUtxvXV","bigweb_js_scopelink.md":"Cri87Xvv","bigweb_js_symbol.md":"UL2UH1np","bigweb_js_this.md":"B8VghyLb","bigweb_js_throttling.md":"CM4lJn4g","bigweb_js_typeconvert.md":"N9P1D0Cd","bigweb_js_typeof.md":"DWNwFNr0","bigweb_js_v8garbage.md":"C1klxmBl","bigweb_js_valuepass.md":"CizkGPj6","bigweb_js_variableobject.md":"CRfqVr_7","bigweb_node_compress-response.md":"DyA0bDei","bigweb_node_index.md":"B_HnquZz","bigweb_node_mongodb.md":"DUdmfOy-","bigweb_node_nvm-iterm.md":"Iox-iSw_","bigweb_node_p1.md":"Day-Egpf","bigweb_node_phantom-dep-cli.md":"y19E0bZY","bigweb_node_standard-node-cli.md":"DO9AaD1n","bigweb_node_前端接口神器之 json-server 详细使用指南 - megasu - 博客园.md":"BthQkKKA","bigweb_performance_cdn.md":"BbQ8beMh","bigweb_performance_dnspre.md":"D2IqAMDZ","bigweb_performance_image.md":"DCqo4ixN","bigweb_performance_index.md":"DSp5hIjq","bigweb_performance_internet.md":"BAICaUsl","bigweb_performance_lazyload.md":"BiLxNxX1","bigweb_performance_monitor.md":"DQPA0n5B","bigweb_performance_preload.md":"beRMyx3g","bigweb_performance_prerender.md":"B-WeKhIF","bigweb_performance_ssr.md":"D7IofkjQ","bigweb_performance_throttling.md":"C0pCHeQq","bigweb_regexp_index.md":"IcWpHxFA","bigweb_regexp_p1.md":"Cdhhhxa9","bigweb_vue_communicate.md":"NMT6LiFv","bigweb_vue_compile.md":"CEoPqOTL","bigweb_vue_computed.md":"DCKct1xB","bigweb_vue_dep.md":"D0FtCEsK","bigweb_vue_diff.md":"BahE4n0N","bigweb_vue_extend.md":"BBWLj9yU","bigweb_vue_hook.md":"Bt2CnyV_","bigweb_vue_index.md":"Df15kJWy","bigweb_vue_keep-alive.md":"I1jxlUAK","bigweb_vue_mechanism.md":"Dhc0Qi-W","bigweb_vue_mixin.md":"DNtt4S5A","bigweb_vue_responsive.md":"BRhroUTr","bigweb_vue_routing.md":"BKBAT_rr","bigweb_vue_showif.md":"D1kcizXv","bigweb_vue_vnode.md":"BCWX9T3_","bigweb_vueresource_index.md":"BDN6mB7T","coding_algorithm_addstring.md":"Dy4zQnH1","coding_algorithm_feibo1.md":"CoN_3oyc","coding_algorithm_feibo2.md":"jG_7AdnG","coding_algorithm_headsort.md":"Dx-lpWNv","coding_algorithm_index.md":"zb8tnxjQ","coding_algorithm_judgesymmetrytree.md":"BKnVa1IB","coding_algorithm_linkreserve.md":"BoOJ8lE-","coding_algorithm_mergesort.md":"Bzb-uQ7g","coding_algorithm_publicstring.md":"C55pSt93","coding_algorithm_publicstringlen.md":"D7qYMank","coding_algorithm_quicksort.md":"DDdOQrLv","coding_algorithm_treeleveltraverse.md":"C6eiGIHp","coding_dotnet_dotnetviavscode.md":"BYp4NC6P","coding_dotnet_index.md":"DhXBOw-L","coding_github_git删除当前分支下的所有历史版本与log并同步至github_git如何清除历史版本.md":"BOXi8Ghp","coding_github_index.md":"Bh-L6u1A","coding_github_sourcetree ssh密钥缓存问题解决.md":"CPfLlD0w","computerbase_algorithm_index.md":"DRQG0W40","computerbase_algorithm_sort.md":"IpgVZJuw","computerbase_design_abstractfactory.md":"Byb6_AzH","computerbase_design_factory.md":"EdR_RvH_","computerbase_design_index.md":"CUogsA8d","computerbase_design_single.md":"tacBD_eq","computerbase_internet_clength.md":"mbjLz8VI","computerbase_internet_http.md":"B4qINtUi","computerbase_internet_index.md":"BEo-nrcn","computerbase_internet_tcp-udp.md":"D9noCsMZ","computerbase_internet_tcp.md":"CfU_1_nq","computerbase_internet_udp.md":"Bji4DXni","computerbase_leetcode_index.md":"BGXKxf6_","computerbase_os_communicate.md":"CDzQ3YPo","computerbase_os_deadlock.md":"4RE7QgUH","computerbase_os_difprothr.md":"ygvybhyU","computerbase_os_index.md":"D_r60cml","computerbase_os_process.md":"WSOWlR3r","computerbase_os_thread.md":"CnccsQcs","configdoc_newyear_2022.md":"DrV0_ylZ","configdoc_show_bole.md":"19MTxqZV","configdoc_show_sw.md":"Cv41VCLO","configdoc_show_whyfe-2024.md":"Dt-DMPFg","configdoc_show_whyfe.md":"NTdEzVHz","configdoc_top_address.md":"CndMVrlY","configdoc_top_campusproblem.md":"ae_W3L1M","configdoc_top_notice.md":"BmXHyZX7","essay_dev_2024-blog-perf.md":"-L3NFfhh","group.md":"CUCjnZd2","index.md":"DHYynGqP","interview_code_debounce-throttle.md":"CRRyLbQf","interview_code_index.md":"CXOdG-_U","interview_code_kmp.md":"C6IUK40T","interview_code_middle-center.md":"CJh1AzAZ","interview_code_myclock.md":"DBT8Q3qI","interview_code_transfer.md":"CLlSBhBH","interview_code_treetraverse.md":"82_6Z6tR","interview_internet_index.md":"rnpzv5gj","interview_mini_differentweb.md":"DSc1Vwb-","interview_mini_feature.md":"vzfoN77w","interview_mini_index.md":"Kh-sjAae","interview_mini_principle.md":"u-MTb5Ym","interview_offer_index.md":"DM-gdqZZ","interview_offer_p50.md":"CHmVSYS0","interview_offer_p53-2.md":"8RtEpKas","interview_offer_p54.md":"74IkeVvc","interview_offer_p55-1.md":"CjRU1Z9T","interview_offer_p55.md":"HNqXQkhO","interview_offer_p58.md":"CMnLUpT_","interview_os_index.md":"Cwj5f7XH","interview_other_engineering.md":"rt_2_tAj","interview_other_index.md":"C7iNZjwJ","interview_other_inputurl.md":"OEsj_C5P","interview_other_judgetype.md":"D-G9R9Mi","interview_other_object.md":"DY4MpPpa","interview_other_promote.md":"DMaX3Kn8","interview_other_prototype.md":"AFVsY5g1","interview_performance_firstscreenrender.md":"CljGz-sc","interview_performance_index.md":"DynURTlS","interview_vue_index.md":"BD8I4xKr","stocks_precisionheadshot_index.md":"Bq5vxs_B","stocks_sentimentcore_index.md":"Dv1EzCNf","technology_learn_array-buffer.md":"DnIwOB78","technology_learn_cnnc.md":"D6DQ5c_o","technology_learn_copy-branch.md":"Ba6o1290","technology_learn_deepin-wemeet.md":"BCUw1Zvi","technology_learn_deploy-preview-pr.md":"C5RKIwAn","technology_learn_ep2-docker.md":"DUlXmiSr","technology_learn_eslint-plugin.md":"fb19TBkx","technology_learn_esm-require.md":"hXsOHPfT","technology_learn_faas.md":"BYdkwieO","technology_learn_fixed-page.md":"BIn08b4F","technology_learn_forof-idx.md":"tS4FoyZL","technology_learn_git-base.md":"D2NXRaQc","technology_learn_index.md":"D8VlDtZQ","technology_learn_jpg-compress.md":"DR9H7AK8","technology_learn_js-cover.md":"usxPPszF","technology_learn_jsencrypt.md":"BV4KzmhD","technology_learn_loadenv.md":"OAYQnaSf","technology_learn_mergefile.md":"Cf3N8CmA","technology_learn_mid-autumn-festival.md":"bqiWIfJ8","technology_learn_mini-lottie.md":"CBrP1J3K","technology_learn_node-require-json.md":"DM0PKjj_","technology_learn_nodejs-getting-started.md":"DYRJWVdj","technology_learn_png-compress.md":"CqJ8XNrF","technology_learn_pnpm-issue-githubactions.md":"BYfhkFwo","technology_learn_qiniu-imgbed.md":"A0sKZyS5","technology_learn_qiniu-oss.md":"BsdvBxri","technology_learn_ssh-no-pwd-login.md":"CevYYEel","technology_learn_tool-methods.md":"J8iYU4mP","technology_learn_tx-serverless-node.md":"57qYI-da","technology_learn_tx-serverless-static.md":"DTHO89F9","technology_learn_upyun.md":"B2KnwJpM","technology_learn_ux.md":"C56DD0KY","technology_learn_vite-plugin-monitor1.md":"C3pMJIOI","technology_learn_vite-plugin-monitor2.md":"D2ezfNZP","technology_learn_vite-plugin-monitor3.md":"BSbT7bfU","technology_learn_vite-react-js.md":"D6gUcbgi","technology_learn_vitepress-plugin-rss.md":"aVXcjCYI","technology_learn_webapck2vite.md":"3-cxVrYK","technology_learn_webapck2vite2.md":"BKAa0Phz","technology_learn_window-var.md":"DiIFMzjj","technology_learn_yanglegeyang.md":"BwNVDx7r","technology_source_core-decorators-1.md":"BcrLsArE","technology_source_core-decorators-2.md":"BY8bUkF6","technology_source_core-decorators-3.md":"DnEnE79w","technology_source_file-saver-source.md":"JCz4OuBj","technology_source_index.md":"Dj4PnNDJ","technology_source_objectid.md":"gYhX78JA","technology_source_vite-loadenv.md":"Br0OV248","technology_study_chrome-debug1.md":"DV8mnIWg","technology_study_chrome-debug2.md":"ql2YO3ig","technology_study_chrome-debug3.md":"DIB5aOXJ","technology_study_chrome-debug4.md":"Tr7v-3Qt","technology_study_chrome-debug5.md":"CQwf_3Hs","technology_study_chrome-debug6.md":"BpJk8tt2","technology_study_design-patterns0.md":"Ciz-Fd8Q","technology_study_design-patterns1.md":"DwfAhQre","technology_study_design-patterns2.md":"D6E4vP3J","technology_study_http-proxy-fail.md":"BP2OqRzn","technology_study_index.md":"Cp638cg1","technology_study_nvm-ls-remote.md":"DXkJ9-vV","technology_study_ts-decorators.md":"CmYTC75B","technology_theory_index.md":"C69koheZ","technology_theory_serverless.md":"Cj3xUlqt","technology_tpl_index.md":"Bm2zyUXf","technology_tpl_uni-vue3-cli_1.md":"DBRf6HQ9","technology_tpl_uni-vue3-cli_2.md":"H9skpW1i","technology_tpl_uni-vue3-cli_3.md":"BJ58Qya1","technology_tpl_vite-vue3-template.md":"Co2nbLo9","technology_tpl_web-sdk-tpl.md":"CjFS2zQ2","technology_works_codenote.md":"Y84bAPTa","technology_works_escheck.md":"CG4mCMod","technology_works_eslint-plugin-todo-ddl.md":"BuCiPW6Q","technology_works_ewuit.md":"C2BGWKWy","technology_works_fs-cli.md":"G1MC8I2B","technology_works_html-inline-js-transform.md":"bKEO8pHh","technology_works_index.md":"BwMvZRD3","technology_works_node-cli.md":"QsXwBLF6","technology_works_online-resume.md":"Kp06UjqN","technology_works_share-snippets.md":"BijDe95D","technology_works_sm-cli.md":"DBCv_5UF","technology_works_snippets.md":"CLvJxTd7","technology_works_theme.md":"b4r5awHW","technology_works_vitepress-plugin-pagefind.md":"Q_eo6T-n","weekly_index.md":"Ch8Jkqjp","works_time-lover_index.md":"C6hzEbpT","works_time-lover_timelover-1.md":"fPwQhjCs","works_time-lover_timelover-2.md":"Cr6chK9V","works_time-tools_index.md":"C2UzexFY","works_time-tools_time-tools-1.md":"BfnxLDQ3","works_time-tools_time-tools-10.md":"BiwAvdhf","works_time-tools_time-tools-11.md":"DGXrNemW","works_time-tools_time-tools-12.md":"C9qCxxla","works_time-tools_time-tools-13.md":"Bmo0biiU","works_time-tools_time-tools-14.md":"DTMeKR0o","works_time-tools_time-tools-15.md":"C5C6yEj6","works_time-tools_time-tools-2.md":"DkNSnpZi","works_time-tools_time-tools-3.md":"DLhvGNNn","works_time-tools_time-tools-4.md":"BhhDxVrT","works_time-tools_time-tools-5.md":"fTpyzH4c","works_time-tools_time-tools-6.md":"dbSIZt19","works_time-tools_time-tools-7.md":"B58oFuBT","works_time-tools_time-tools-8.md":"7rRjmSTR","works_time-tools_time-tools-9.md":"DSUFy_MX"}
