{"aboutme.md":"B-GPsF3u","ai_coze_juejin-hot-rank-bot.md":"DSfbO_NC","ai_stable-diffusion_index.md":"C4faAHOr","ai_stable-diffusion_mac-install.md":"DCrAPF2n","bigweb_browser_block.md":"B2TO03k-","bigweb_browser_cache.md":"BclZgw7O","bigweb_browser_chrome-devtools-study.md":"Jy8ciMpS","bigweb_browser_core.md":"BG1RNqdw","bigweb_browser_cors.md":"CoRMu4gC","bigweb_browser_eventloop.md":"B1wssZEl","bigweb_browser_index.md":"Bd70Xxc4","bigweb_browser_problem.md":"BHnN7VtH","bigweb_browser_render.md":"6j8ZasjI","bigweb_browser_safe.md":"DSYG2FCg","bigweb_browser_storage.md":"BjvC6Ogj","bigweb_bun_bun-shell.md":"Bt__ri_Q","bigweb_css_bfc.md":"CxlS2W-a","bigweb_css_box.md":"DDlAQf8A","bigweb_css_flex.md":"CPCleOoS","bigweb_css_ifc.md":"C-IEWuE7","bigweb_css_index.md":"DHT92GMQ","bigweb_css_level.md":"D4sYjojM","bigweb_css_p1.md":"DEA_vzHC","bigweb_css_p2.md":"C3XLv6Ds","bigweb_css_pseudo-class.md":"De6LJlma","bigweb_css_pseudo-element.md":"Bt80ZXN3","bigweb_css_reflow.md":"B-wz8zv8","bigweb_css_selectors.md":"Bi7PndGS","bigweb_es6_index.md":"DLyPwI1_","bigweb_html_index.md":"zUmECsXo","bigweb_html_semantic.md":"DvDvNXtB","bigweb_idea.md":"DIQDj8dz","bigweb_js_apply.md":"Ccu6cb4c","bigweb_js_arrowfun.md":"DOeW8Zy1","bigweb_js_async.md":"UQZTEFRV","bigweb_js_asyncawait.md":"hnhYiwfC","bigweb_js_blob.md":"rDqtliuy","bigweb_js_changearr.md":"CDDp2ani","bigweb_js_clock.md":"FBHvb7ng","bigweb_js_closure.md":"BaTeMCnr","bigweb_js_closureuse.md":"BVpGNoKc","bigweb_js_copy.md":"CHEqavOQ","bigweb_js_currying.md":"BruLXvFL","bigweb_js_deepclone.md":"ByXirlCg","bigweb_js_delete.md":"DJJu9eNQ","bigweb_js_diff-for-in-of.md":"0oTrzFi0","bigweb_js_duplicate.md":"DD33KAIP","bigweb_js_ecmathis.md":"Dv-0O-Uw","bigweb_js_equal.md":"UDM4o39P","bigweb_js_equala.md":"DkVs4KTb","bigweb_js_es6.md":"B6xxtdOq","bigweb_js_es6_.md":"DaEFHjql","bigweb_js_event.md":"CaasfMc5","bigweb_js_eventloop.md":"CVBgsSx6","bigweb_js_float.md":"B0UPBnnt","bigweb_js_garbage.md":"BTD97_N0","bigweb_js_getbool.md":"CrrrnprO","bigweb_js_getelement.md":"DIzoOwWS","bigweb_js_immed-setinterval.md":"BiQYQcI1","bigweb_js_index copy.md":"A_--J-IC","bigweb_js_index.md":"BsyRe-zw","bigweb_js_inherit.md":"CzNL8r2l","bigweb_js_instanceof copy.md":"BahUTwJl","bigweb_js_instanceof.md":"CgZX-Nn9","bigweb_js_judgearr.md":"k5TwxPBW","bigweb_js_judgedate.md":"DTW8vSS1","bigweb_js_judgeobj.md":"D20Kg5Xe","bigweb_js_likearray.md":"eeIFcwiC","bigweb_js_mergerequest.md":"BhR7ZPl4","bigweb_js_module.md":"CBnagq4q","bigweb_js_myapply.md":"DwD3E66h","bigweb_js_mybind.md":"B0L2ut8S","bigweb_js_mycall.md":"JxA4005t","bigweb_js_mynew.md":"C0HWsPs1","bigweb_js_nullobj.md":"CYLUcbyC","bigweb_js_numnotequal.md":"Ds7DQkQ4","bigweb_js_objdiffprim.md":"0AjnL4SW","bigweb_js_objparam.md":"BA3XeFZK","bigweb_js_onload-ready.md":"OG5tdqmu","bigweb_js_p0.md":"Cdye-0n_","bigweb_js_p1.md":"BCaJxO5H","bigweb_js_p2.md":"DF4h6mnx","bigweb_js_p3.md":"DBSy-nNy","bigweb_js_p4.md":"C1EVcEIu","bigweb_js_p5.md":"pPuA1OBl","bigweb_js_primitivetype.md":"CSvGXU_2","bigweb_js_promise copy.md":"DjprsTCT","bigweb_js_promise.md":"Bw0OCwOY","bigweb_js_promiseall.md":"D05Mr4zA","bigweb_js_prototype.md":"B1h7bS2P","bigweb_js_runcontext.md":"vyutkS2M","bigweb_js_runstack.md":"4vyFGIIX","bigweb_js_scope.md":"U6sNAKvM","bigweb_js_scopelink.md":"CTP31d5K","bigweb_js_symbol.md":"88A9p9lV","bigweb_js_this.md":"DNv-TdWD","bigweb_js_throttling.md":"B0d9554X","bigweb_js_typeconvert.md":"C1VJRuO8","bigweb_js_typeof.md":"BRMWnMP5","bigweb_js_v8garbage.md":"BYFhvtT5","bigweb_js_valuepass.md":"KfbGGr-0","bigweb_js_variableobject.md":"Bn7zpV2Z","bigweb_node_compress-response.md":"3B6KGRI1","bigweb_node_index.md":"BlU224ru","bigweb_node_mongodb.md":"DvEabeZR","bigweb_node_nvm-iterm.md":"du96rTzD","bigweb_node_p1.md":"DQTBaVfy","bigweb_node_phantom-dep-cli.md":"DkOfvbQO","bigweb_node_standard-node-cli.md":"Cd353MEv","bigweb_node_前端接口神器之 json-server 详细使用指南 - megasu - 博客园.md":"CESmVGyH","bigweb_performance_cdn.md":"LZCfhLmo","bigweb_performance_dnspre.md":"DFMi-kU1","bigweb_performance_image.md":"BDrWs446","bigweb_performance_index.md":"xwCcMKZC","bigweb_performance_internet.md":"BOmeKE0Y","bigweb_performance_lazyload.md":"DB2np5vg","bigweb_performance_monitor.md":"jyn_WOTr","bigweb_performance_preload.md":"CQwA2vZg","bigweb_performance_prerender.md":"jZj9PUxD","bigweb_performance_ssr.md":"BgR-SsO5","bigweb_performance_throttling.md":"CkMLw-Gi","bigweb_regexp_index.md":"CgSXHgVs","bigweb_regexp_p1.md":"ColZHs4w","bigweb_vue_communicate.md":"M65Th9-w","bigweb_vue_compile.md":"uk3UCOik","bigweb_vue_computed.md":"DyEdd0Sw","bigweb_vue_dep.md":"Bd5Tbx9e","bigweb_vue_diff.md":"D3eakVBN","bigweb_vue_extend.md":"DrbDmsjv","bigweb_vue_hook.md":"C2bj-UZG","bigweb_vue_index.md":"C19h0Glz","bigweb_vue_keep-alive.md":"D7dvS1Kg","bigweb_vue_mechanism.md":"DvtbqzPx","bigweb_vue_mixin.md":"OH0YU_KB","bigweb_vue_responsive.md":"DxZ8ftqT","bigweb_vue_routing.md":"CRJFRbEg","bigweb_vue_showif.md":"Cm63Kh-l","bigweb_vue_vnode.md":"C_-8STHg","bigweb_vueresource_index.md":"BLxvwtDG","coding_algorithm_addstring.md":"C4X0imG0","coding_algorithm_feibo1.md":"30867pe9","coding_algorithm_feibo2.md":"BABVjq2Y","coding_algorithm_headsort.md":"cq1yLfMt","coding_algorithm_index.md":"_plpQgwl","coding_algorithm_judgesymmetrytree.md":"D-vyP4Xb","coding_algorithm_linkreserve.md":"CkXzh8lb","coding_algorithm_mergesort.md":"CRnnlHC7","coding_algorithm_publicstring.md":"An-372O5","coding_algorithm_publicstringlen.md":"B2mEDP1C","coding_algorithm_quicksort.md":"Cw8Ou_23","coding_algorithm_treeleveltraverse.md":"z0OvxAbG","coding_dotnet_dotnetviavscode.md":"O0Wr4o-v","coding_dotnet_index.md":"BbAMZGEM","coding_github_git删除当前分支下的所有历史版本与log并同步至github_git如何清除历史版本.md":"Ql9CQgw_","coding_github_index.md":"HlYGaIjI","coding_github_sourcetree ssh密钥缓存问题解决.md":"Dp4x1iIx","computerbase_algorithm_index.md":"B4l9sOk_","computerbase_algorithm_sort.md":"9DcNVKUg","computerbase_design_abstractfactory.md":"espEE3vP","computerbase_design_factory.md":"B8yXqrrG","computerbase_design_index.md":"BlHao1IB","computerbase_design_single.md":"DIocQ9Sd","computerbase_internet_clength.md":"CTxWsLy_","computerbase_internet_http.md":"D7YAefQU","computerbase_internet_index.md":"fhUrB8RN","computerbase_internet_tcp-udp.md":"DYV32caw","computerbase_internet_tcp.md":"D1b7dH1g","computerbase_internet_udp.md":"a7a-HNoU","computerbase_leetcode_index.md":"B6og7qWq","computerbase_os_communicate.md":"Ds6CSmG5","computerbase_os_deadlock.md":"dNFoQOYI","computerbase_os_difprothr.md":"D9c8uHne","computerbase_os_index.md":"CEnHhLtQ","computerbase_os_process.md":"B5-3TGoS","computerbase_os_thread.md":"Dbdc6dsg","configdoc_newyear_2022.md":"De7sahDj","configdoc_show_bole.md":"CIbitIi5","configdoc_show_sw.md":"ecbCnRHX","configdoc_show_whyfe-2024.md":"BGZ5pVPc","configdoc_show_whyfe.md":"De3e_gVx","configdoc_top_address.md":"sfBRLvlW","configdoc_top_campusproblem.md":"BP-CLO9D","configdoc_top_notice.md":"DlIt4aH2","essay_dev_2024-blog-perf.md":"DOUyuXo1","group.md":"2I1SsONP","index.md":"CQfyyMWv","interview_code_debounce-throttle.md":"ihQ0XNTS","interview_code_index.md":"NKp3d5eC","interview_code_kmp.md":"DeYPepsj","interview_code_middle-center.md":"CtPnrQ0U","interview_code_myclock.md":"CZcGIN7K","interview_code_transfer.md":"DqjLXMCS","interview_code_treetraverse.md":"Bq1jrZp9","interview_internet_index.md":"BWoEKbma","interview_mini_differentweb.md":"Bphrr1vI","interview_mini_feature.md":"Bo7mgIZB","interview_mini_index.md":"BPDlvJN-","interview_mini_principle.md":"ooApt0DU","interview_offer_index.md":"CWFI0zIj","interview_offer_p50.md":"BsvgHnKj","interview_offer_p53-2.md":"CpU6cQ0M","interview_offer_p54.md":"C5iNAci-","interview_offer_p55-1.md":"Bujh1iCc","interview_offer_p55.md":"D4Cbbbzk","interview_offer_p58.md":"DVmobjwf","interview_os_index.md":"D7mBIsKo","interview_other_engineering.md":"nQSfNLBq","interview_other_index.md":"Di7gF19z","interview_other_inputurl.md":"Cfyyfc2W","interview_other_judgetype.md":"czUIuUmD","interview_other_object.md":"Gn-Bjb4m","interview_other_promote.md":"DSAYnZ-6","interview_other_prototype.md":"R3mYNTQ3","interview_performance_firstscreenrender.md":"x8BfOg23","interview_performance_index.md":"BJwqMsO2","interview_vue_index.md":"ChQUbn61","stocks_precisionheadshot_index.md":"n0KnMrkQ","stocks_sentimentcore_index.md":"COhybub9","technology_learn_array-buffer.md":"DzmLXz-y","technology_learn_cnnc.md":"yuaHoj7N","technology_learn_copy-branch.md":"DzoakZpY","technology_learn_deepin-wemeet.md":"CFEERUmB","technology_learn_deploy-preview-pr.md":"auDyUasw","technology_learn_ep2-docker.md":"BPZPHfdm","technology_learn_eslint-plugin.md":"DaA_x9-K","technology_learn_esm-require.md":"B4weFom8","technology_learn_faas.md":"q96H1QCN","technology_learn_fixed-page.md":"BQH-q244","technology_learn_forof-idx.md":"CTi2IEc0","technology_learn_git-base.md":"C41VCjk7","technology_learn_index.md":"BlqramDZ","technology_learn_jpg-compress.md":"CppTSOlP","technology_learn_js-cover.md":"BWeFYHGV","technology_learn_jsencrypt.md":"BOHasqRs","technology_learn_loadenv.md":"DYxNUCme","technology_learn_mergefile.md":"BpE5xdFQ","technology_learn_mid-autumn-festival.md":"BYTt5hTY","technology_learn_mini-lottie.md":"Ds8D5MTQ","technology_learn_node-require-json.md":"BE12ZiTk","technology_learn_nodejs-getting-started.md":"uBwBKJJP","technology_learn_png-compress.md":"C3Sian78","technology_learn_pnpm-issue-githubactions.md":"DWqjkRQq","technology_learn_qiniu-imgbed.md":"CNZm0B4v","technology_learn_qiniu-oss.md":"DSH-1jDb","technology_learn_ssh-no-pwd-login.md":"DId5vZw6","technology_learn_tool-methods.md":"CSXrxA3H","technology_learn_tx-serverless-node.md":"C5doVJeH","technology_learn_tx-serverless-static.md":"Cfcn8q8h","technology_learn_upyun.md":"D6_MDbMw","technology_learn_ux.md":"CoJ2_lkB","technology_learn_vite-plugin-monitor1.md":"D3RTwvKB","technology_learn_vite-plugin-monitor2.md":"819HbHfj","technology_learn_vite-plugin-monitor3.md":"C56Na3bT","technology_learn_vite-react-js.md":"DRLcacnP","technology_learn_vitepress-plugin-rss.md":"CciUT0yq","technology_learn_webapck2vite.md":"DwtvPe5j","technology_learn_webapck2vite2.md":"Ctr16_bi","technology_learn_window-var.md":"DYmqmGL_","technology_learn_yanglegeyang.md":"NodnEEaf","technology_source_core-decorators-1.md":"_MD7bvVk","technology_source_core-decorators-2.md":"BmowBz1x","technology_source_core-decorators-3.md":"B6D6aZIG","technology_source_file-saver-source.md":"B-xGhMjf","technology_source_index.md":"aioVT3DO","technology_source_objectid.md":"BdpvDzVj","technology_source_vite-loadenv.md":"Bm6hLP1O","technology_study_chrome-debug1.md":"AH8KZhG9","technology_study_chrome-debug2.md":"DPJteotK","technology_study_chrome-debug3.md":"Cdb4_PaY","technology_study_chrome-debug4.md":"DG1dx_62","technology_study_chrome-debug5.md":"CSB0fqHr","technology_study_chrome-debug6.md":"Bpctd7dF","technology_study_design-patterns0.md":"BmU05otq","technology_study_design-patterns1.md":"Brl0iHe0","technology_study_design-patterns2.md":"DIefHGGD","technology_study_http-proxy-fail.md":"CpFoUi0X","technology_study_index.md":"BKfTE_Jf","technology_study_nvm-ls-remote.md":"DSmwOKOx","technology_study_ts-decorators.md":"DI2ZjFmy","technology_theory_index.md":"DyzeiZIF","technology_theory_serverless.md":"BxXAmdaV","technology_tpl_index.md":"BaPO9HAI","technology_tpl_uni-vue3-cli_1.md":"aRjG67Kl","technology_tpl_uni-vue3-cli_2.md":"DqavYNqG","technology_tpl_uni-vue3-cli_3.md":"BwdWN1YT","technology_tpl_vite-vue3-template.md":"CNma7tsJ","technology_tpl_web-sdk-tpl.md":"Bj8LXiVT","technology_works_codenote.md":"CUYSYgIE","technology_works_escheck.md":"CHySN66W","technology_works_eslint-plugin-todo-ddl.md":"CeL4q_ft","technology_works_ewuit.md":"-wftrqdM","technology_works_fs-cli.md":"DCr9ZyJG","technology_works_html-inline-js-transform.md":"BYppIy_R","technology_works_index.md":"XDcuWiTt","technology_works_node-cli.md":"C-A5oOjM","technology_works_online-resume.md":"DiDeq2a1","technology_works_share-snippets.md":"Ck46AnpA","technology_works_sm-cli.md":"m_koXQDl","technology_works_snippets.md":"aU_Bbpza","technology_works_theme.md":"uIgfxrQ5","technology_works_vitepress-plugin-pagefind.md":"BsP-UPY8","weekly_index.md":"ywnc-zxo","works_time-lover_index.md":"B5yGTZLG","works_time-lover_timelover-1.md":"DNqr4L6O","works_time-lover_timelover-2.md":"dcxhKdDZ","works_time-tools_index.md":"B1vbEQZy","works_time-tools_time-tools-1.md":"CKQEhyg6","works_time-tools_time-tools-10.md":"pkHX5WWx","works_time-tools_time-tools-11.md":"DosbuR7c","works_time-tools_time-tools-12.md":"BY9PjZq3","works_time-tools_time-tools-13.md":"Dwo61Dg5","works_time-tools_time-tools-14.md":"I6a3GWAU","works_time-tools_time-tools-15.md":"BId7hEji","works_time-tools_time-tools-2.md":"EUv9vS5Y","works_time-tools_time-tools-3.md":"DmUgDAqv","works_time-tools_time-tools-4.md":"DuRKOK_0","works_time-tools_time-tools-5.md":"DMd2y9et","works_time-tools_time-tools-6.md":"CJvyvONa","works_time-tools_time-tools-7.md":"HHPeYCKh","works_time-tools_time-tools-8.md":"l4l1oVMP","works_time-tools_time-tools-9.md":"Dl6LfLZf"}
